Workbook
Name Unchangable: 'Working Filter Page'!$B$4:$E$4
Name Unchangable: 'Easy Filter Page'!$B$4:$E$4
Name Unchangable: 'Dungeon Loot'!$A$1:$I$1

Sheet Easy Filter Page
C1: Loot Table Calculator | D1: Filter Value | E1: Filter Rarity | G1: Filter Category
A2: =IF(E2="Mundane", 1, IF(E2="Common", 2, IF(E2="Uncommon", 3, IF(E2="Rare", 4, IF(E2="Very Rare", 5, IF(E2="Legendary", 6, 0)))))) -> 1 | C2: Lowest: | D2: 100 | E2: Mundane | G2: Wondrous Item
A3: =IF(E3="Mundane", 1, IF(E3="Common", 2, IF(E3="Uncommon", 3, IF(E3="Rare", 4, IF(E3="Very Rare", 5, IF(E3="Legendary", 6, 0)))))) -> 3 | C3: Highest: | D3: 10000 | E3: Uncommon | G3: Weapon
A4: D100 Roll | B4: Name | C4: Description | D4: Est. Value | E4: Rarity | F4: Weight | G4: Category | H4: Properties | I4: Requirements | J4: Author | K4: Rarity Number
A5: 42644 | B5: =IFERROR(__xludf.DUMMYFUNCTION("FILTER('Dungeon Loot'!A2:K1004, ('Dungeon Loot'!C2:C1004 > D2), ('Dungeon Loot'!C2:C1004 < D3), ('Dungeon Loot'!J2:J1004 >= A2), ('Dungeon Loot'!J2:J1004 <= A3), ('Dungeon Loot'!F2:F1004=G2) + ('Dungeon Loot'!F2:F1004=G3))"),"Hidden Blade Bracer") -> Hidden Blade Bracer | C5: =IFERROR(__xludf.DUMMYFUNCTION("""COMPUTED_VALUE"""),"Concealed punching dagger-bracer") -> Concealed punching dagger-bracer | D5: =IFERROR(__xludf.DUMMYFUNCTION("""COMPUTED_VALUE"""),200.0) -> 200 | E5: =IFERROR(__xludf.DUMMYFUNCTION("""COMPUTED_VALUE"""),"Common") -> Common | F5: =IFERROR(__xludf.DUMMYFUNCTION("""COMPUTED_VALUE"""),2.0) -> 2 | G5: =IFERROR(__xludf.DUMMYFUNCTION("""COMPUTED_VALUE"""),"Weapon") -> Weapon | H5: =IFERROR(__xludf.DUMMYFUNCTION("""COMPUTED_VALUE"""),"1d4 Piercing - Finesse, Light - Range: 20/60 When you attack and hit a creature that is surprised with this dagger, it must make a Constitution saving throw DC 18. On a failed save, the target takes an extra 2d4 damage from your attack.") -> 1d4 Piercing - Finesse, Light - Range: 20/60 When you attack and hit a creature that is surprised with this dagger, it must make a Constitution saving throw DC 18. On a failed save, the target takes an extra 2d4 damage from your attack. | K5: =IFERROR(__xludf.DUMMYFUNCTION("""COMPUTED_VALUE"""),2.0) -> 2
A6: 11-20 | B6: =IFERROR(__xludf.DUMMYFUNCTION("""COMPUTED_VALUE"""),"Neverfull Waterskin") -> Neverfull Waterskin | C6: =IFERROR(__xludf.DUMMYFUNCTION("""COMPUTED_VALUE"""),"Neverfull Waterskin (It's always half empty.)") -> Neverfull Waterskin (It's always half empty.) | D6: =IFERROR(__xludf.DUMMYFUNCTION("""COMPUTED_VALUE"""),200.0) -> 200 | E6: =IFERROR(__xludf.DUMMYFUNCTION("""COMPUTED_VALUE"""),"Uncommon") -> Uncommon | F6: =IFERROR(__xludf.DUMMYFUNCTION("""COMPUTED_VALUE"""),1.0) -> 1 | G6: =IFERROR(__xludf.DUMMYFUNCTION("""COMPUTED_VALUE"""),"Wondrous Item") -> Wondrous Item | K6: =IFERROR(__xludf.DUMMYFUNCTION("""COMPUTED_VALUE"""),3.0) -> 3
A7: 21 - 30 | B7: =IFERROR(__xludf.DUMMYFUNCTION("""COMPUTED_VALUE"""),"Alchemy Jug") -> Alchemy Jug | C7: =IFERROR(__xludf.DUMMYFUNCTION("""COMPUTED_VALUE"""),"This ceramic jug appears to be able to hold a gallon of liquid and weighs 12 pounds whether full or empty. Sloshing sounds can be heard from within the jug when it is shaken, even if the jug is empty. You can use an action and name one liquid from the tab"&"le below to cause the jug to produce the chosen liquid. Afterward, you can uncork the jug as an action and pour that liquid out, up to 2 gallons per minute. The maximum amount of liquid the jug can produce depends on the liquid you named. Once the jug sta"&"rts producing a liquid, it can't produce a different one, or more of one that has reached its maximum, until the next dawn. ") -> This ceramic jug appears to be able to hold a gallon of liquid and weighs 12 pounds whether full or empty. Sloshing sounds can be heard from within the jug when it is shaken, even if the jug is empty. You can use an action and name one liquid from the table below to cause the jug to produce the chosen liquid. Afterward, you can uncork the jug as an action and pour that liquid out, up to 2 gallons per minute. The maximum amount of liquid the jug can produce depends on the liquid you named. Once the jug starts producing a liquid, it can't produce a different one, or more of one that has reached its maximum, until the next dawn. | D7: =IFERROR(__xludf.DUMMYFUNCTION("""COMPUTED_VALUE"""),6000.0) -> 6000 | E7: =IFERROR(__xludf.DUMMYFUNCTION("""COMPUTED_VALUE"""),"Uncommon") -> Uncommon | F7: =IFERROR(__xludf.DUMMYFUNCTION("""COMPUTED_VALUE"""),1.0) -> 1 | G7: =IFERROR(__xludf.DUMMYFUNCTION("""COMPUTED_VALUE"""),"Wondrous Item") -> Wondrous Item | J7: =IFERROR(__xludf.DUMMYFUNCTION("""COMPUTED_VALUE"""),"DMG") -> DMG | K7: =IFERROR(__xludf.DUMMYFUNCTION("""COMPUTED_VALUE"""),3.0) -> 3
A8: 31 - 40 | B8: =IFERROR(__xludf.DUMMYFUNCTION("""COMPUTED_VALUE"""),"Bag of Holding") -> Bag of Holding | C8: =IFERROR(__xludf.DUMMYFUNCTION("""COMPUTED_VALUE"""),"This bag has an interior space considerably larger than its outside dimensions, roughly 2 feet in diameter at the mouth and 4 feet deep. The bag can hold up to 500 pounds, not exceeding a volume of 64 cubic feet. The bag weighs 15 pounds, regardless of it"&"s contents. Retrieving an item from the bag requires an action. If the bag is overloaded, pierced, or torn, it ruptures and is destroyed, and its contents are scattered in the Astral Plane. If the bag is turned inside out, its contents spill forth, unharm"&"ed, but the bag must be put right before it can be used again. Breathing creatures inside the bag can survive up to a number of minutes equal to 10 divided by the number of creatures (minimum 1 minute), after which time they begin to suffocate. Placing a "&"bag of holding inside an extradimensional space created by a Heward's handy haversack, portable hole, or similar item instantly destroys both items and opens a gate to the Astral Plane. The gate originates where the one item was placed inside the other. A"&"ny creature within 10 feet of the gate is sucked through it to a random location on the Astral Plane. The gate then closes. The gate is one-way only and can't be reopened. ") -> This bag has an interior space considerably larger than its outside dimensions, roughly 2 feet in diameter at the mouth and 4 feet deep. The bag can hold up to 500 pounds, not exceeding a volume of 64 cubic feet. The bag weighs 15 pounds, regardless of its contents. Retrieving an item from the bag requires an action. If the bag is overloaded, pierced, or torn, it ruptures and is destroyed, and its contents are scattered in the Astral Plane. If the bag is turned inside out, its contents spill forth, unharmed, but the bag must be put right before it can be used again. Breathing creatures inside the bag can survive up to a number of minutes equal to 10 divided by the number of creatures (minimum 1 minute), after which time they begin to suffocate. Placing a bag of holding inside an extradimensional space created by a Heward's handy haversack, portable hole, or similar item instantly destroys both items and opens a gate to the Astral Plane. The gate originates where the one item was placed inside the other. Any creature within 10 feet of the gate is sucked through it to a random location on the Astral Plane. The gate then closes. The gate is one-way only and can't be reopened. | D8: =IFERROR(__xludf.DUMMYFUNCTION("""COMPUTED_VALUE"""),4000.0) -> 4000 | E8: =IFERROR(__xludf.DUMMYFUNCTION("""COMPUTED_VALUE"""),"Uncommon") -> Uncommon | F8: =IFERROR(__xludf.DUMMYFUNCTION("""COMPUTED_VALUE"""),15.0) -> 15 | G8: =IFERROR(__xludf.DUMMYFUNCTION("""COMPUTED_VALUE"""),"Wondrous Item") -> Wondrous Item | J8: =IFERROR(__xludf.DUMMYFUNCTION("""COMPUTED_VALUE"""),"DMG") -> DMG | K8: =IFERROR(__xludf.DUMMYFUNCTION("""COMPUTED_VALUE"""),3.0) -> 3
A9: 41 - 50 | B9: =IFERROR(__xludf.DUMMYFUNCTION("""COMPUTED_VALUE"""),"Bag of Tricks, Grey") -> Bag of Tricks, Grey | C9: =IFERROR(__xludf.DUMMYFUNCTION("""COMPUTED_VALUE"""),"This ordinary gray cloth bag appears to be empty. Reaching inside the bag, however, reveals the presence of a small, fuzzy object. You can use an action to pull the fuzzy object from the bag and throw it up to 20 feet. When the object lands, it transforms"&" into a creature you determine by rolling a d8 and consulting the table that corresponds to the bag’s color. The creature vanishes at the next dawn or when it is reduced to 0 hit points. The creature is friendly to you and your companions, and it acts on "&"your turn. You can use a bonus action to command how the creature moves and what action it takes on its next turn, or to give it general orders, such as to attack your enemies. In the absence of such orders, the creature acts in a fashion appropriate to i"&"ts nature. Once three fuzzy objects have been pulled from the bag, the bag cannot be used again until the next dawn. ") -> This ordinary gray cloth bag appears to be empty. Reaching inside the bag, however, reveals the presence of a small, fuzzy object. You can use an action to pull the fuzzy object from the bag and throw it up to 20 feet. When the object lands, it transforms into a creature you determine by rolling a d8 and consulting the table that corresponds to the bag’s color. The creature vanishes at the next dawn or when it is reduced to 0 hit points. The creature is friendly to you and your companions, and it acts on your turn. You can use a bonus action to command how the creature moves and what action it takes on its next turn, or to give it general orders, such as to attack your enemies. In the absence of such orders, the creature acts in a fashion appropriate to its nature. Once three fuzzy objects have been pulled from the bag, the bag cannot be used again until the next dawn. | D9: =IFERROR(__xludf.DUMMYFUNCTION("""COMPUTED_VALUE"""),900.0) -> 900 | E9: =IFERROR(__xludf.DUMMYFUNCTION("""COMPUTED_VALUE"""),"Uncommon") -> Uncommon | F9: =IFERROR(__xludf.DUMMYFUNCTION("""COMPUTED_VALUE"""),0.5) -> 0.5 | G9: =IFERROR(__xludf.DUMMYFUNCTION("""COMPUTED_VALUE"""),"Wondrous Item") -> Wondrous Item | J9: =IFERROR(__xludf.DUMMYFUNCTION("""COMPUTED_VALUE"""),"DMG") -> DMG | K9: =IFERROR(__xludf.DUMMYFUNCTION("""COMPUTED_VALUE"""),3.0) -> 3
A10: 51 - 55 | B10: =IFERROR(__xludf.DUMMYFUNCTION("""COMPUTED_VALUE"""),"Bat Sack") -> Bat Sack | C10: =IFERROR(__xludf.DUMMYFUNCTION("""COMPUTED_VALUE"""),"Witch’s Mad Sack of Bats – releases swarm of bats") -> Witch’s Mad Sack of Bats – releases swarm of bats | D10: =IFERROR(__xludf.DUMMYFUNCTION("""COMPUTED_VALUE"""),300.0) -> 300 | E10: =IFERROR(__xludf.DUMMYFUNCTION("""COMPUTED_VALUE"""),"Uncommon") -> Uncommon | F10: =IFERROR(__xludf.DUMMYFUNCTION("""COMPUTED_VALUE"""),1.0) -> 1 | G10: =IFERROR(__xludf.DUMMYFUNCTION("""COMPUTED_VALUE"""),"Wondrous Item") -> Wondrous Item | J10: =IFERROR(__xludf.DUMMYFUNCTION("""COMPUTED_VALUE"""),"PlatypusPal") -> PlatypusPal | K10: =IFERROR(__xludf.DUMMYFUNCTION("""COMPUTED_VALUE"""),3.0) -> 3
A11: 56 - 60 | B11: =IFERROR(__xludf.DUMMYFUNCTION("""COMPUTED_VALUE"""),"Bear Claw Boots") -> Bear Claw Boots | C11: =IFERROR(__xludf.DUMMYFUNCTION("""COMPUTED_VALUE"""),"A pair of dark leather boots upon which a curious gnomish mechanism has been fastened around. There is a small lever on the side of the ankle that, when toggled, extends on each boot a set of sharp mountaineering claws. The boots are sized for medium huma"&"noid but the mechanism itself would be easy enough for a blacksmith to scale up or down.") -> A pair of dark leather boots upon which a curious gnomish mechanism has been fastened around. There is a small lever on the side of the ankle that, when toggled, extends on each boot a set of sharp mountaineering claws. The boots are sized for medium humanoid but the mechanism itself would be easy enough for a blacksmith to scale up or down. | D11: =IFERROR(__xludf.DUMMYFUNCTION("""COMPUTED_VALUE"""),300.0) -> 300 | E11: =IFERROR(__xludf.DUMMYFUNCTION("""COMPUTED_VALUE"""),"Uncommon") -> Uncommon | F11: =IFERROR(__xludf.DUMMYFUNCTION("""COMPUTED_VALUE"""),4.0) -> 4 | G11: =IFERROR(__xludf.DUMMYFUNCTION("""COMPUTED_VALUE"""),"Wondrous Item") -> Wondrous Item | H11: =IFERROR(__xludf.DUMMYFUNCTION("""COMPUTED_VALUE"""),"The mountaineering claws provide a +2 circumstance bonus to climb checks. This bonus can be used in addition to a Climber's Kit.") -> The mountaineering claws provide a +2 circumstance bonus to climb checks. This bonus can be used in addition to a Climber's Kit. | J11: =IFERROR(__xludf.DUMMYFUNCTION("""COMPUTED_VALUE"""),"Uberbeard") -> Uberbeard | K11: =IFERROR(__xludf.DUMMYFUNCTION("""COMPUTED_VALUE"""),3.0) -> 3
A12: 61 - 65 | B12: =IFERROR(__xludf.DUMMYFUNCTION("""COMPUTED_VALUE"""),"Boots of Elvenkind") -> Boots of Elvenkind | C12: =IFERROR(__xludf.DUMMYFUNCTION("""COMPUTED_VALUE"""),"While you wear these boots, your steps make no sound, regardless of the surface you are moving across. You also have advantage on Dexterity (Stealth) checks that rely on moving silently. ") -> While you wear these boots, your steps make no sound, regardless of the surface you are moving across. You also have advantage on Dexterity (Stealth) checks that rely on moving silently. | D12: =IFERROR(__xludf.DUMMYFUNCTION("""COMPUTED_VALUE"""),2500.0) -> 2500 | E12: =IFERROR(__xludf.DUMMYFUNCTION("""COMPUTED_VALUE"""),"Uncommon") -> Uncommon | F12: =IFERROR(__xludf.DUMMYFUNCTION("""COMPUTED_VALUE"""),1.0) -> 1 | G12: =IFERROR(__xludf.DUMMYFUNCTION("""COMPUTED_VALUE"""),"Wondrous Item") -> Wondrous Item | J12: =IFERROR(__xludf.DUMMYFUNCTION("""COMPUTED_VALUE"""),"DMG") -> DMG | K12: =IFERROR(__xludf.DUMMYFUNCTION("""COMPUTED_VALUE"""),3.0) -> 3
A13: 66 - 70 | B13: =IFERROR(__xludf.DUMMYFUNCTION("""COMPUTED_VALUE"""),"Boots of Striding and Springing") -> Boots of Striding and Springing | C13: =IFERROR(__xludf.DUMMYFUNCTION("""COMPUTED_VALUE"""),"A pair of tan boots which are fastened around the foot with three adjustable belts. The inner sole of these boots feels springy to the touch and seems to mould itself around the user's foot for a fit so comfortable it's like walking on the clouds.") -> A pair of tan boots which are fastened around the foot with three adjustable belts. The inner sole of these boots feels springy to the touch and seems to mould itself around the user's foot for a fit so comfortable it's like walking on the clouds. | D13: =IFERROR(__xludf.DUMMYFUNCTION("""COMPUTED_VALUE"""),5000.0) -> 5000 | E13: =IFERROR(__xludf.DUMMYFUNCTION("""COMPUTED_VALUE"""),"Uncommon") -> Uncommon | F13: =IFERROR(__xludf.DUMMYFUNCTION("""COMPUTED_VALUE"""),1.0) -> 1 | G13: =IFERROR(__xludf.DUMMYFUNCTION("""COMPUTED_VALUE"""),"Wondrous Item") -> Wondrous Item | H13: =IFERROR(__xludf.DUMMYFUNCTION("""COMPUTED_VALUE"""),"While you wear these boots, your walking speed becomes 30 feet, unless your walking speed is higher, and your speed isn't reduced if you are encumbered or wearing heavy armor. In addition, you can jump three times the normal distance, though you can't jum"&"p farther than your remaining movement would allow.") -> While you wear these boots, your walking speed becomes 30 feet, unless your walking speed is higher, and your speed isn't reduced if you are encumbered or wearing heavy armor. In addition, you can jump three times the normal distance, though you can't jump farther than your remaining movement would allow. | I13: =IFERROR(__xludf.DUMMYFUNCTION("""COMPUTED_VALUE"""),"Requires Attunement") -> Requires Attunement | J13: =IFERROR(__xludf.DUMMYFUNCTION("""COMPUTED_VALUE"""),"DMG") -> DMG | K13: =IFERROR(__xludf.DUMMYFUNCTION("""COMPUTED_VALUE"""),3.0) -> 3
A14: 71 - 75 | B14: =IFERROR(__xludf.DUMMYFUNCTION("""COMPUTED_VALUE"""),"Boots of the Winterlands") -> Boots of the Winterlands | C14: =IFERROR(__xludf.DUMMYFUNCTION("""COMPUTED_VALUE"""),"A pair of hide boots lined with dense, warm white fur. The eyelet for each bootlace is patterned with small gemstones and the sole of the boot is spiked so as to benefit the user over icy and unstable terrain. These furred boots are snug and feel quite wa"&"rm. ") -> A pair of hide boots lined with dense, warm white fur. The eyelet for each bootlace is patterned with small gemstones and the sole of the boot is spiked so as to benefit the user over icy and unstable terrain. These furred boots are snug and feel quite warm. | D14: =IFERROR(__xludf.DUMMYFUNCTION("""COMPUTED_VALUE"""),2500.0) -> 2500 | E14: =IFERROR(__xludf.DUMMYFUNCTION("""COMPUTED_VALUE"""),"Uncommon") -> Uncommon | F14: =IFERROR(__xludf.DUMMYFUNCTION("""COMPUTED_VALUE"""),1.0) -> 1 | G14: =IFERROR(__xludf.DUMMYFUNCTION("""COMPUTED_VALUE"""),"Wondrous Item") -> Wondrous Item | H14: =IFERROR(__xludf.DUMMYFUNCTION("""COMPUTED_VALUE"""),"See DMG page 156.") -> See DMG page 156. | I14: =IFERROR(__xludf.DUMMYFUNCTION("""COMPUTED_VALUE"""),"Requires Attunement") -> Requires Attunement | J14: =IFERROR(__xludf.DUMMYFUNCTION("""COMPUTED_VALUE"""),"DMG") -> DMG | K14: =IFERROR(__xludf.DUMMYFUNCTION("""COMPUTED_VALUE"""),3.0) -> 3
A15: 76 - 80 | B15: =IFERROR(__xludf.DUMMYFUNCTION("""COMPUTED_VALUE"""),"Bracers of Archery") -> Bracers of Archery | C15: =IFERROR(__xludf.DUMMYFUNCTION("""COMPUTED_VALUE"""),"While wearing these bracers, you have proficiency with the longbow and shortbow, and you gain a +2 bonus to damage rolls on ranged attacks made with such weapons.") -> While wearing these bracers, you have proficiency with the longbow and shortbow, and you gain a +2 bonus to damage rolls on ranged attacks made with such weapons. | D15: =IFERROR(__xludf.DUMMYFUNCTION("""COMPUTED_VALUE"""),1500.0) -> 1500 | E15: =IFERROR(__xludf.DUMMYFUNCTION("""COMPUTED_VALUE"""),"Uncommon") -> Uncommon | F15: =IFERROR(__xludf.DUMMYFUNCTION("""COMPUTED_VALUE"""),1.0) -> 1 | G15: =IFERROR(__xludf.DUMMYFUNCTION("""COMPUTED_VALUE"""),"Wondrous Item") -> Wondrous Item | I15: =IFERROR(__xludf.DUMMYFUNCTION("""COMPUTED_VALUE"""),"Requires Attunement") -> Requires Attunement | J15: =IFERROR(__xludf.DUMMYFUNCTION("""COMPUTED_VALUE"""),"DMG") -> DMG | K15: =IFERROR(__xludf.DUMMYFUNCTION("""COMPUTED_VALUE"""),3.0) -> 3
A16: 81 - 85 | B16: =IFERROR(__xludf.DUMMYFUNCTION("""COMPUTED_VALUE"""),"Bracers of Binding") -> Bracers of Binding | C16: =IFERROR(__xludf.DUMMYFUNCTION("""COMPUTED_VALUE"""),"The bracers appear to be Bracers of Specialization, but when donned, bind the wearer wrists together, making it quite difficult to wield a weapon or cast a spell. These bracers are sometimes offered as rewards for services rendered by the Drow. The recipi"&"ent, believing them to be very powerful, will often don them before examinating them. At this point, the drow find it amusing to conjure a hook horror. ") -> The bracers appear to be Bracers of Specialization, but when donned, bind the wearer wrists together, making it quite difficult to wield a weapon or cast a spell. These bracers are sometimes offered as rewards for services rendered by the Drow. The recipient, believing them to be very powerful, will often don them before examinating them. At this point, the drow find it amusing to conjure a hook horror. | D16: =IFERROR(__xludf.DUMMYFUNCTION("""COMPUTED_VALUE"""),300.0) -> 300 | E16: =IFERROR(__xludf.DUMMYFUNCTION("""COMPUTED_VALUE"""),"Uncommon") -> Uncommon | F16: =IFERROR(__xludf.DUMMYFUNCTION("""COMPUTED_VALUE"""),"n/a") -> n/a | G16: =IFERROR(__xludf.DUMMYFUNCTION("""COMPUTED_VALUE"""),"Wondrous Item") -> Wondrous Item | H16: =IFERROR(__xludf.DUMMYFUNCTION("""COMPUTED_VALUE"""),"lower damage by 5 points, increase spell failure to 75% and give the wearer a +5 penalty to THACO. Since they are cursed, they can't be unequiped without a Remove Curse spell or the services of a priest") -> lower damage by 5 points, increase spell failure to 75% and give the wearer a +5 penalty to THACO. Since they are cursed, they can't be unequiped without a Remove Curse spell or the services of a priest | J16: =IFERROR(__xludf.DUMMYFUNCTION("""COMPUTED_VALUE"""),"BGII") -> BGII | K16: =IFERROR(__xludf.DUMMYFUNCTION("""COMPUTED_VALUE"""),3.0) -> 3
A17: 86 - 90 | B17: =IFERROR(__xludf.DUMMYFUNCTION("""COMPUTED_VALUE"""),"Brooch of Shielding") -> Brooch of Shielding | C17: =IFERROR(__xludf.DUMMYFUNCTION("""COMPUTED_VALUE"""),"While wearing this brooch, you have resistance to force damage, and you have immunity to damage from the magic missile spell. ") -> While wearing this brooch, you have resistance to force damage, and you have immunity to damage from the magic missile spell. | D17: =IFERROR(__xludf.DUMMYFUNCTION("""COMPUTED_VALUE"""),7500.0) -> 7500 | E17: =IFERROR(__xludf.DUMMYFUNCTION("""COMPUTED_VALUE"""),"Uncommon") -> Uncommon | F17: =IFERROR(__xludf.DUMMYFUNCTION("""COMPUTED_VALUE"""),"n/a") -> n/a | G17: =IFERROR(__xludf.DUMMYFUNCTION("""COMPUTED_VALUE"""),"Wondrous Item") -> Wondrous Item | I17: =IFERROR(__xludf.DUMMYFUNCTION("""COMPUTED_VALUE"""),"Requires Attunement") -> Requires Attunement | J17: =IFERROR(__xludf.DUMMYFUNCTION("""COMPUTED_VALUE"""),"DMG") -> DMG | K17: =IFERROR(__xludf.DUMMYFUNCTION("""COMPUTED_VALUE"""),3.0) -> 3
A18: 91 | B18: =IFERROR(__xludf.DUMMYFUNCTION("""COMPUTED_VALUE"""),"Broom of Flying") -> Broom of Flying | C18: =IFERROR(__xludf.DUMMYFUNCTION("""COMPUTED_VALUE"""),"This wooden broom functions like a mundane broom until you stand astride it and speak its command word. It then hovers beneath you and can be ridden in the air. The broom stops hovering when you land. You can send the broom to travel alone to a destinatio"&"n within 1 mile of you if you speak the command word, name the location, and are familiar with that place. The broom comes back to you when you speak another command word, provided that the broom is still within 1 mile of you. ") -> This wooden broom functions like a mundane broom until you stand astride it and speak its command word. It then hovers beneath you and can be ridden in the air. The broom stops hovering when you land. You can send the broom to travel alone to a destination within 1 mile of you if you speak the command word, name the location, and are familiar with that place. The broom comes back to you when you speak another command word, provided that the broom is still within 1 mile of you. | D18: =IFERROR(__xludf.DUMMYFUNCTION("""COMPUTED_VALUE"""),8000.0) -> 8000 | E18: =IFERROR(__xludf.DUMMYFUNCTION("""COMPUTED_VALUE"""),"Uncommon") -> Uncommon | F18: =IFERROR(__xludf.DUMMYFUNCTION("""COMPUTED_VALUE"""),3.0) -> 3 | G18: =IFERROR(__xludf.DUMMYFUNCTION("""COMPUTED_VALUE"""),"Wondrous Item") -> Wondrous Item | H18: =IFERROR(__xludf.DUMMYFUNCTION("""COMPUTED_VALUE"""),"It has a flying speed of 50 feet. It can carry up to 400 pounds, but its flying speed becomes 30 feet while carrying over 200 pounds. ") -> It has a flying speed of 50 feet. It can carry up to 400 pounds, but its flying speed becomes 30 feet while carrying over 200 pounds. | J18: =IFERROR(__xludf.DUMMYFUNCTION("""COMPUTED_VALUE"""),"DMG") -> DMG | K18: =IFERROR(__xludf.DUMMYFUNCTION("""COMPUTED_VALUE"""),3.0) -> 3
A19: 92 | B19: =IFERROR(__xludf.DUMMYFUNCTION("""COMPUTED_VALUE"""),"Cap of Water Breathing") -> Cap of Water Breathing | C19: =IFERROR(__xludf.DUMMYFUNCTION("""COMPUTED_VALUE"""),"The word “STYX” is sewn into the inner headband of this cap.") -> The word “STYX” is sewn into the inner headband of this cap. | D19: =IFERROR(__xludf.DUMMYFUNCTION("""COMPUTED_VALUE"""),1000.0) -> 1000 | E19: =IFERROR(__xludf.DUMMYFUNCTION("""COMPUTED_VALUE"""),"Uncommon") -> Uncommon | F19: =IFERROR(__xludf.DUMMYFUNCTION("""COMPUTED_VALUE"""),1.0) -> 1 | G19: =IFERROR(__xludf.DUMMYFUNCTION("""COMPUTED_VALUE"""),"Wondrous Item") -> Wondrous Item | H19: =IFERROR(__xludf.DUMMYFUNCTION("""COMPUTED_VALUE"""),"While wearing this cap underwater you can speak its command word as an action to create a bubble of air arround your head. It allows you to breathing normally underwater. This bubble stays with you until you speak the command word again, the cap is remove"&"d or you are no longer underwater.") -> While wearing this cap underwater you can speak its command word as an action to create a bubble of air arround your head. It allows you to breathing normally underwater. This bubble stays with you until you speak the command word again, the cap is removed or you are no longer underwater. | J19: =IFERROR(__xludf.DUMMYFUNCTION("""COMPUTED_VALUE"""),"DMG") -> DMG | K19: =IFERROR(__xludf.DUMMYFUNCTION("""COMPUTED_VALUE"""),3.0) -> 3
A20: 93 | B20: =IFERROR(__xludf.DUMMYFUNCTION("""COMPUTED_VALUE"""),"Edible Greatsword") -> Edible Greatsword | C20: =IFERROR(__xludf.DUMMYFUNCTION("""COMPUTED_VALUE"""),"Works like a normal greatsword. Great tasting and low in calories! Regenerates 6 inches per day.") -> Works like a normal greatsword. Great tasting and low in calories! Regenerates 6 inches per day. | D20: =IFERROR(__xludf.DUMMYFUNCTION("""COMPUTED_VALUE"""),400.0) -> 400 | E20: =IFERROR(__xludf.DUMMYFUNCTION("""COMPUTED_VALUE"""),"Uncommon") -> Uncommon | F20: =IFERROR(__xludf.DUMMYFUNCTION("""COMPUTED_VALUE"""),6.0) -> 6 | G20: =IFERROR(__xludf.DUMMYFUNCTION("""COMPUTED_VALUE"""),"Weapon") -> Weapon | H20: =IFERROR(__xludf.DUMMYFUNCTION("""COMPUTED_VALUE"""),"2d6 Slashing - Heavy - Two-Handed") -> 2d6 Slashing - Heavy - Two-Handed | I20: =IFERROR(__xludf.DUMMYFUNCTION("""COMPUTED_VALUE"""),"Martial Weapon Expertise") -> Martial Weapon Expertise | J20: =IFERROR(__xludf.DUMMYFUNCTION("""COMPUTED_VALUE"""),"Uberbeard") -> Uberbeard | K20: =IFERROR(__xludf.DUMMYFUNCTION("""COMPUTED_VALUE"""),3.0) -> 3
A21: 94 | B21: =IFERROR(__xludf.DUMMYFUNCTION("""COMPUTED_VALUE"""),"Sentient Dagger of Sneaking") -> Sentient Dagger of Sneaking | C21: =IFERROR(__xludf.DUMMYFUNCTION("""COMPUTED_VALUE"""),"This sentient dagger attempts to help anytime it's owner tries to sneak by whistling inconspicuously. For some reason it seems to have been discarded.") -> This sentient dagger attempts to help anytime it's owner tries to sneak by whistling inconspicuously. For some reason it seems to have been discarded. | D21: =IFERROR(__xludf.DUMMYFUNCTION("""COMPUTED_VALUE"""),300.0) -> 300 | E21: =IFERROR(__xludf.DUMMYFUNCTION("""COMPUTED_VALUE"""),"Uncommon") -> Uncommon | F21: =IFERROR(__xludf.DUMMYFUNCTION("""COMPUTED_VALUE"""),1.0) -> 1 | G21: =IFERROR(__xludf.DUMMYFUNCTION("""COMPUTED_VALUE"""),"Weapon") -> Weapon | H21: =IFERROR(__xludf.DUMMYFUNCTION("""COMPUTED_VALUE"""),"1d4 Piercing - Finesse, Light - Range: 20/60") -> 1d4 Piercing - Finesse, Light - Range: 20/60 | J21: =IFERROR(__xludf.DUMMYFUNCTION("""COMPUTED_VALUE"""),"Uberbeard") -> Uberbeard | K21: =IFERROR(__xludf.DUMMYFUNCTION("""COMPUTED_VALUE"""),3.0) -> 3
A22: 95 | B22: =IFERROR(__xludf.DUMMYFUNCTION("""COMPUTED_VALUE"""),"Boomerang of Retrieval") -> Boomerang of Retrieval | C22: =IFERROR(__xludf.DUMMYFUNCTION("""COMPUTED_VALUE"""),"This otherwise normal looking boomerang has a sense of arcana deep within it's dark oak core. Researching it's history will reveal that this is, in fact, one of many created by a local wizard who was frustrated at being unable to throw a normal boomerang "&"in such a way that it returned naturally.") -> This otherwise normal looking boomerang has a sense of arcana deep within it's dark oak core. Researching it's history will reveal that this is, in fact, one of many created by a local wizard who was frustrated at being unable to throw a normal boomerang in such a way that it returned naturally. | D22: =IFERROR(__xludf.DUMMYFUNCTION("""COMPUTED_VALUE"""),180.0) -> 180 | E22: =IFERROR(__xludf.DUMMYFUNCTION("""COMPUTED_VALUE"""),"Uncommon") -> Uncommon | F22: =IFERROR(__xludf.DUMMYFUNCTION("""COMPUTED_VALUE"""),2.0) -> 2 | G22: =IFERROR(__xludf.DUMMYFUNCTION("""COMPUTED_VALUE"""),"Weapon") -> Weapon | H22: =IFERROR(__xludf.DUMMYFUNCTION("""COMPUTED_VALUE"""),"1d6 Bludgeoning (+1 force damage) - Thrown (Range: 30/90) Special: Does not require direct line of sight, due to a curved trajectory. Unlike a normal boomerang, the boomerang of retrieval will always return to you after you make a ranged attack with it, "&"even if you hit.") -> 1d6 Bludgeoning (+1 force damage) - Thrown (Range: 30/90) Special: Does not require direct line of sight, due to a curved trajectory. Unlike a normal boomerang, the boomerang of retrieval will always return to you after you make a ranged attack with it, even if you hit. | J22: =IFERROR(__xludf.DUMMYFUNCTION("""COMPUTED_VALUE"""),"D&D Wiki") -> D&D Wiki | K22: =IFERROR(__xludf.DUMMYFUNCTION("""COMPUTED_VALUE"""),3.0) -> 3
A23: 96 | B23: =IFERROR(__xludf.DUMMYFUNCTION("""COMPUTED_VALUE"""),"Gnome Timepiece") -> Gnome Timepiece | C23: =IFERROR(__xludf.DUMMYFUNCTION("""COMPUTED_VALUE"""),"A magical time-keeping device produced by a Gnomish artisan. Opening this circular locket allows you to check the current time based on where a delicate hand is pointing. On one half of the circular face is an ornate night's sky with a crescent moon indic"&"ating midnight. On the other half is a blue sky, with a bright sun indicating mid-day. It's unclear how the magic has been infused with the device, as no arcane presence is detectable, but pulling the silver panel off the back of the locket simply exposes"&" a number of delicate, ticking gears. Gnome magic is compicated.") -> A magical time-keeping device produced by a Gnomish artisan. Opening this circular locket allows you to check the current time based on where a delicate hand is pointing. On one half of the circular face is an ornate night's sky with a crescent moon indicating midnight. On the other half is a blue sky, with a bright sun indicating mid-day. It's unclear how the magic has been infused with the device, as no arcane presence is detectable, but pulling the silver panel off the back of the locket simply exposes a number of delicate, ticking gears. Gnome magic is compicated. | D23: =IFERROR(__xludf.DUMMYFUNCTION("""COMPUTED_VALUE"""),150.0) -> 150 | E23: =IFERROR(__xludf.DUMMYFUNCTION("""COMPUTED_VALUE"""),"Uncommon") -> Uncommon | F23: =IFERROR(__xludf.DUMMYFUNCTION("""COMPUTED_VALUE"""),"n/a") -> n/a | G23: =IFERROR(__xludf.DUMMYFUNCTION("""COMPUTED_VALUE"""),"Wondrous Item") -> Wondrous Item | J23: =IFERROR(__xludf.DUMMYFUNCTION("""COMPUTED_VALUE"""),"Uberbeard") -> Uberbeard | K23: =IFERROR(__xludf.DUMMYFUNCTION("""COMPUTED_VALUE"""),3.0) -> 3
A24: 97 | B24: =IFERROR(__xludf.DUMMYFUNCTION("""COMPUTED_VALUE"""),"The Living Lantern") -> The Living Lantern | C24: =IFERROR(__xludf.DUMMYFUNCTION("""COMPUTED_VALUE"""),"An an ordinary candle lamp with a glass surround and handle.") -> An an ordinary candle lamp with a glass surround and handle. | D24: =IFERROR(__xludf.DUMMYFUNCTION("""COMPUTED_VALUE"""),1000.0) -> 1000 | E24: =IFERROR(__xludf.DUMMYFUNCTION("""COMPUTED_VALUE"""),"Uncommon") -> Uncommon | F24: =IFERROR(__xludf.DUMMYFUNCTION("""COMPUTED_VALUE"""),2.0) -> 2 | G24: =IFERROR(__xludf.DUMMYFUNCTION("""COMPUTED_VALUE"""),"Wondrous Item") -> Wondrous Item | H24: =IFERROR(__xludf.DUMMYFUNCTION("""COMPUTED_VALUE"""),"When used the candle on this lantern does not burn down and the luminosity of the lantern is far beyond what a simple hooded lantern should be capable of. Once lit, the lantern slowly grows in light level until it is dangerous to look at directly. It also"&" slowly comes to consciousness, as if being roused from a deep sleep. After an hour, the lantern is fully sapient and can parlay with the party. It has a deep desire to burn everything flammable (and can do so), but may be tempered with the promise of bei"&"ng kept alight for longer. For the first 30 minutes it provides light at a range of 60/90 ft. This grows by 30 ft for every 30 minutes after. If left on for more than 3 hours the lantern becomes so hot it will set fire to anything flammable in a 5 foot r"&"ange. It can be extinguished with a command word written on the base of the lantern.") -> When used the candle on this lantern does not burn down and the luminosity of the lantern is far beyond what a simple hooded lantern should be capable of. Once lit, the lantern slowly grows in light level until it is dangerous to look at directly. It also slowly comes to consciousness, as if being roused from a deep sleep. After an hour, the lantern is fully sapient and can parlay with the party. It has a deep desire to burn everything flammable (and can do so), but may be tempered with the promise of being kept alight for longer. For the first 30 minutes it provides light at a range of 60/90 ft. This grows by 30 ft for every 30 minutes after. If left on for more than 3 hours the lantern becomes so hot it will set fire to anything flammable in a 5 foot range. It can be extinguished with a command word written on the base of the lantern. | J24: =IFERROR(__xludf.DUMMYFUNCTION("""COMPUTED_VALUE"""),"Uberbeard") -> Uberbeard | K24: =IFERROR(__xludf.DUMMYFUNCTION("""COMPUTED_VALUE"""),3.0) -> 3
A25: 98 | B25: =IFERROR(__xludf.DUMMYFUNCTION("""COMPUTED_VALUE"""),"Waterskin of Inexplicable Amelioration") -> Waterskin of Inexplicable Amelioration | C25: =IFERROR(__xludf.DUMMYFUNCTION("""COMPUTED_VALUE"""),"A sheep's bladder waterskin. It is lined with a suedelike fabric which has been beautifully stiched with the image of a stag's head. ") -> A sheep's bladder waterskin. It is lined with a suedelike fabric which has been beautifully stiched with the image of a stag's head. | D25: =IFERROR(__xludf.DUMMYFUNCTION("""COMPUTED_VALUE"""),600.0) -> 600 | E25: =IFERROR(__xludf.DUMMYFUNCTION("""COMPUTED_VALUE"""),"Uncommon") -> Uncommon | G25: =IFERROR(__xludf.DUMMYFUNCTION("""COMPUTED_VALUE"""),"Wondrous Item") -> Wondrous Item | H25: =IFERROR(__xludf.DUMMYFUNCTION("""COMPUTED_VALUE"""),"When any liquid is poured into this waterskin it is instantly purified of disease, poison or other potentially harmful contaminents.") -> When any liquid is poured into this waterskin it is instantly purified of disease, poison or other potentially harmful contaminents. | K25: =IFERROR(__xludf.DUMMYFUNCTION("""COMPUTED_VALUE"""),3.0) -> 3
A26: 99 | B26: =IFERROR(__xludf.DUMMYFUNCTION("""COMPUTED_VALUE"""),"Greedy Bag of Holding") -> Greedy Bag of Holding | C26: =IFERROR(__xludf.DUMMYFUNCTION("""COMPUTED_VALUE"""),"This appears to be a common cloth sack about 2 feet by 4 feet in size. ") -> This appears to be a common cloth sack about 2 feet by 4 feet in size. | D26: =IFERROR(__xludf.DUMMYFUNCTION("""COMPUTED_VALUE"""),500.0) -> 500 | E26: =IFERROR(__xludf.DUMMYFUNCTION("""COMPUTED_VALUE"""),"Uncommon") -> Uncommon | F26: =IFERROR(__xludf.DUMMYFUNCTION("""COMPUTED_VALUE"""),15.0) -> 15 | G26: =IFERROR(__xludf.DUMMYFUNCTION("""COMPUTED_VALUE"""),"Wondrous Item") -> Wondrous Item | H26: =IFERROR(__xludf.DUMMYFUNCTION("""COMPUTED_VALUE"""),"This functions as a normal Bag of Holding, but for every item you wish to remove from the bag you must put in a silver piece. Any money placed into the bag dissapears almost immediately. It's unclear where the coins go when placed into the bag.") -> This functions as a normal Bag of Holding, but for every item you wish to remove from the bag you must put in a silver piece. Any money placed into the bag dissapears almost immediately. It's unclear where the coins go when placed into the bag. | J26: =IFERROR(__xludf.DUMMYFUNCTION("""COMPUTED_VALUE"""),"William Orfanakos") -> William Orfanakos | K26: =IFERROR(__xludf.DUMMYFUNCTION("""COMPUTED_VALUE"""),3.0) -> 3
A27: 100

Sheet Dungeon Loot
A1: Item | B1: Description | C1: Est. Value | D1: Rarity | E1: Weight | F1: Category | G1: Properties | H1: Requirements | I1: Author | J1: Rarity Number
A2: Oily Rags | B2: Three oily rags in an old wicker basket. | C2: 0.2 | D2: Mundane | E2: n/a | F2: Treasure | I2: Uberbeard | J2: =IF(D2="Mundane", 1, IF(D2="Common", 2, IF(D2="Uncommon", 3, IF(D2="Rare", 4, IF(D2="Very Rare", 5, IF(D2="Legendary", 6, 100)))))) -> 1
A3: Pickle | B3: On the floor, you find a single pickle wrapped in an oily paper bag. It has a strong distinct smell, but otherwise seems like a normal pickle. | C3: 0.05 | D3: Mundane | E3: 1 | F3: Treasure | I3: Unknown | J3: =IF(D3="Mundane", 1, IF(D3="Common", 2, IF(D3="Uncommon", 3, IF(D3="Rare", 4, IF(D3="Very Rare", 5, IF(D3="Legendary", 6, 100)))))) -> 1
A4: Ancient Sword | B4: A used, slightly rusted double-bladed sword. | C4: 2 | D4: Mundane | E4: 3 | F4: Weapon | G4: 1d4 Piercing - Finesse, Light | I4: PlatypusPal | J4: =IF(D4="Mundane", 1, IF(D4="Common", 2, IF(D4="Uncommon", 3, IF(D4="Rare", 4, IF(D4="Very Rare", 5, IF(D4="Legendary", 6, 100)))))) -> 1
A5: Andar Gem | B5: Andar is hard and durable, yielding translucent gems that flash green-red or brown-red when properly faceted. | C5: 15 | D5: Mundane | E5: n/a | F5: Treasure | I5: Baldur's Gate | J5: =IF(D5="Mundane", 1, IF(D5="Common", 2, IF(D5="Uncommon", 3, IF(D5="Rare", 4, IF(D5="Very Rare", 5, IF(D5="Legendary", 6, 100)))))) -> 1
A6: Banded Agate Gem | B6: A round translucent white gemstone with a ring of striped brown through its center. | C6: 10 | D6: Mundane | E6: n/a | F6: Treasure | I6: DMG | J6: =IF(D6="Mundane", 1, IF(D6="Common", 2, IF(D6="Uncommon", 3, IF(D6="Rare", 4, IF(D6="Very Rare", 5, IF(D6="Legendary", 6, 100)))))) -> 1
A7: Barrel o' Eels | B7: A large barrel of pickled eels. The barrel can be re-used, but it's unlikely the smell of pickled eel will ever truly be washed out. | C7: 5 | D7: Mundane | E7: 35 | F7: Treasure | I7: Uberbeard | J7: =IF(D7="Mundane", 1, IF(D7="Common", 2, IF(D7="Uncommon", 3, IF(D7="Rare", 4, IF(D7="Very Rare", 5, IF(D7="Legendary", 6, 100)))))) -> 1
A8: Barrel o' Nails | B8: A newly crafted barrel filled with iron nails. Might be difficult for the players to get this around if they don't have a cart. | C8: 5 | D8: Mundane | E8: 40 | F8: Treasure | I8: Uberbeard | J8: =IF(D8="Mundane", 1, IF(D8="Common", 2, IF(D8="Uncommon", 3, IF(D8="Rare", 4, IF(D8="Very Rare", 5, IF(D8="Legendary", 6, 100)))))) -> 1
A9: Beaver Pelts | B9: A string of eight beaver pelts. | C9: 1 | D9: Mundane | E9: 20 | F9: Treasure | I9: Uberbeard | J9: =IF(D9="Mundane", 1, IF(D9="Common", 2, IF(D9="Uncommon", 3, IF(D9="Rare", 4, IF(D9="Very Rare", 5, IF(D9="Legendary", 6, 100)))))) -> 1
A10: Belt | B10: An old leather belt. | C10: 0.15 | D10: Mundane | E10: 1 | F10: Treasure | I10: Uberbeard | J10: =IF(D10="Mundane", 1, IF(D10="Common", 2, IF(D10="Uncommon", 3, IF(D10="Rare", 4, IF(D10="Very Rare", 5, IF(D10="Legendary", 6, 100)))))) -> 1
A11: Black Velvet Mask | B11: An ornate black velvet mask sitched with silver thread. | C11: 25 | D11: Mundane | E11: n/a | F11: Treasure | I11: DMG | J11: =IF(D11="Mundane", 1, IF(D11="Common", 2, IF(D11="Uncommon", 3, IF(D11="Rare", 4, IF(D11="Very Rare", 5, IF(D11="Legendary", 6, 100)))))) -> 1
A12: Blank Scroll | B12: A blank scroll. It could have any spell in the world on it, eventually. The possibilities are endless. | C12: 0.5 | D12: Mundane | E12: n/a | F12: Treasure | I12: Uberbeard | J12: =IF(D12="Mundane", 1, IF(D12="Common", 2, IF(D12="Uncommon", 3, IF(D12="Rare", 4, IF(D12="Very Rare", 5, IF(D12="Legendary", 6, 100)))))) -> 1
A13: Blanket | B13: A thick woolen blanket. Something like this is perfect for wrapping up during those long cold nights spent staring at a cave wall. | C13: 0.35 | D13: Mundane | E13: 3 | F13: Adventuring Gear | I13: PHB | J13: =IF(D13="Mundane", 1, IF(D13="Common", 2, IF(D13="Uncommon", 3, IF(D13="Rare", 4, IF(D13="Very Rare", 5, IF(D13="Legendary", 6, 100)))))) -> 1
A14: Blood Stained Dress | B14: A blood-stained dress which, despite being found in ruins which have lain undisturbed for centuries, is still a vibrant, stunning blue. | C14: 2 | D14: Mundane | E14: 2 | F14: Treasure | I14: Uberbeard | J14: =IF(D14="Mundane", 1, IF(D14="Common", 2, IF(D14="Uncommon", 3, IF(D14="Rare", 4, IF(D14="Very Rare", 5, IF(D14="Legendary", 6, 100)))))) -> 1
A15: Blood-Soaked Book | B15: A blood-soaked book; a partially written history about a long-lost keep on the borderlands. The last written page is done in a different hand, and is scrawled with “The rules have changed!” in large, bold letters. Roughly a third of the book (of 100 pages) has been used. | C15: 5 | D15: Mundane | E15: 1 | F15: Book | H15: Language: Common | I15: Unknown | J15: =IF(D15="Mundane", 1, IF(D15="Common", 2, IF(D15="Uncommon", 3, IF(D15="Rare", 4, IF(D15="Very Rare", 5, IF(D15="Legendary", 6, 100)))))) -> 1
A16: Blue Quartz Gem | B16: A small quartz gemstone shaped in a bevelled square. It is transparent pale blue in color. | C16: 10 | D16: Mundane | E16: n/a | F16: Treasure | I16: DMG | J16: =IF(D16="Mundane", 1, IF(D16="Common", 2, IF(D16="Uncommon", 3, IF(D16="Rare", 4, IF(D16="Very Rare", 5, IF(D16="Legendary", 6, 100)))))) -> 1
A17: Blue Scarf | B17: A finely woven blue wool scarf. | C17: 1 | D17: Mundane | E17: n/a | F17: Treasure | I17: Uberbeard | J17: =IF(D17="Mundane", 1, IF(D17="Common", 2, IF(D17="Uncommon", 3, IF(D17="Rare", 4, IF(D17="Very Rare", 5, IF(D17="Legendary", 6, 100)))))) -> 1
A18: Bone Butter Churn | B18: A butter churn made of bone slats, bound with hoops of silver. A scrimshaw scene depicting a crowd of human villagers beating a Halfling with shovels and hoes wraps around it. | C18: 0.5 | D18: Mundane | E18: 1 | F18: Treasure | I18: Unknown | J18: =IF(D18="Mundane", 1, IF(D18="Common", 2, IF(D18="Uncommon", 3, IF(D18="Rare", 4, IF(D18="Very Rare", 5, IF(D18="Legendary", 6, 100)))))) -> 1
A19: Bone Dice | B19: A pair of engraved bone dice. | C19: 25 | D19: Mundane | E19: n/a | F19: Treasure | I19: DMG | J19: =IF(D19="Mundane", 1, IF(D19="Common", 2, IF(D19="Uncommon", 3, IF(D19="Rare", 4, IF(D19="Very Rare", 5, IF(D19="Legendary", 6, 100)))))) -> 1
A20: Bone Fragments | B20: Bits of bone from an unknown creature. | C20: 0 | D20: Mundane | E20: n/a | F20: Treasure | I20: Uberbeard | J20: =IF(D20="Mundane", 1, IF(D20="Common", 2, IF(D20="Uncommon", 3, IF(D20="Rare", 4, IF(D20="Very Rare", 5, IF(D20="Legendary", 6, 100)))))) -> 1
A21: Bone Needle | B21: A long needle carved out of bone. | C21: 0.25 | D21: Mundane | E21: n/a | F21: Treasure | I21: Uberbeard | J21: =IF(D21="Mundane", 1, IF(D21="Common", 2, IF(D21="Uncommon", 3, IF(D21="Rare", 4, IF(D21="Very Rare", 5, IF(D21="Legendary", 6, 100)))))) -> 1
A22: Broken Sword | B22: This is simply a regular sword that has been partially broken, in combat or however. Most people would just get rid of it, but maybe this sword has a nice hilt or sentimental value. | C22: 0.5 | D22: Mundane | E22: 3 | F22: Weapon | G22: 1d4 Piercing, Finesse, Light | I22: D&D Wiki | J22: =IF(D22="Mundane", 1, IF(D22="Common", 2, IF(D22="Uncommon", 3, IF(D22="Rare", 4, IF(D22="Very Rare", 5, IF(D22="Legendary", 6, 100)))))) -> 1
A23: Candle | B23: Six red wax candles. | C23: 0.01 | D23: Mundane | E23: n/a | F23: Adventuring Gear | G23: For 1 hour, a candle sheds bright light in a 5-foot radius and dim light for an additional 5 feet. | I23: PHB | J23: =IF(D23="Mundane", 1, IF(D23="Common", 2, IF(D23="Uncommon", 3, IF(D23="Rare", 4, IF(D23="Very Rare", 5, IF(D23="Legendary", 6, 100)))))) -> 1
A24: Carved Bone Statuette | B24: A carved ox bone female figure statue on a wooden base. The statue is 16" in height. | C24: 25 | D24: Mundane | E24: 1 | F24: Treasure | I24: DMG | J24: =IF(D24="Mundane", 1, IF(D24="Common", 2, IF(D24="Uncommon", 3, IF(D24="Rare", 4, IF(D24="Very Rare", 5, IF(D24="Legendary", 6, 100)))))) -> 1
A25: Chalk | B25: A small piece of chalk used to draw on any hard surface. | C25: 0.05 | D25: Mundane | E25: n/a | F25: Treasure | I25: Uberbeard | J25: =IF(D25="Mundane", 1, IF(D25="Common", 2, IF(D25="Uncommon", 3, IF(D25="Rare", 4, IF(D25="Very Rare", 5, IF(D25="Legendary", 6, 100)))))) -> 1
A26: Cloth Scrap | B26: An old scrap of cloth from a shirt or sheet of some kind. | C26: 0 | D26: Mundane | E26: n/a | F26: Treasure | I26: Uberbeard | J26: =IF(D26="Mundane", 1, IF(D26="Common", 2, IF(D26="Uncommon", 3, IF(D26="Rare", 4, IF(D26="Very Rare", 5, IF(D26="Legendary", 6, 100)))))) -> 1
A27: Cloth-of-gold Vestments | B27: These holy garments are made of silk interwoven with gold threads. | C27: 25 | D27: Mundane | E27: 3 | F27: Treasure | I27: DMG | J27: =IF(D27="Mundane", 1, IF(D27="Common", 2, IF(D27="Uncommon", 3, IF(D27="Rare", 4, IF(D27="Very Rare", 5, IF(D27="Legendary", 6, 100)))))) -> 1
A28: Comb | B28: A small wooden comb. | C28: 0.2 | D28: Mundane | E28: n/a | F28: Treasure | I28: Uberbeard | J28: =IF(D28="Mundane", 1, IF(D28="Common", 2, IF(D28="Uncommon", 3, IF(D28="Rare", 4, IF(D28="Very Rare", 5, IF(D28="Legendary", 6, 100)))))) -> 1
A29: Cooking Pot | B29: A cast iron cooking pot. It smells like it was last used for soup. | C29: 0.2 | D29: Mundane | E29: 2 | F29: Treasure | I29: Uberbeard | J29: =IF(D29="Mundane", 1, IF(D29="Common", 2, IF(D29="Uncommon", 3, IF(D29="Rare", 4, IF(D29="Very Rare", 5, IF(D29="Legendary", 6, 100)))))) -> 1
A30: Copper Acorns | B30: Heavy, solid copper acorns with perfect natural detail. | C30: 1 | D30: Mundane | E30: 2 | F30: Treasure | G30: These acorns drop from the oak-like trees that sprout on the graves of Copper Dragons. They can be lethal when falling, often embedding themselves in the ground. | I30: /u/gimme_some_sunshine | J30: =IF(D30="Mundane", 1, IF(D30="Common", 2, IF(D30="Uncommon", 3, IF(D30="Rare", 4, IF(D30="Very Rare", 5, IF(D30="Legendary", 6, 100)))))) -> 1
A31: Carved Beads | B31: A string of wooden carved beads, tied into a bracelet. | C31: 4 | D31: Mundane | E31: n/a | F31: Treasure | I31: Uberbeard | J31: 1
A32: Rusty Horseshoe | B32: An old rusty horseshoe, the metal may be worth something. | C32: 1 | D32: Mundane | E32: 0.5 | F32: Treasure | I32: Uberbeard | J32: 1
A33: Copper Ring | B33: A simple piece of jewlery. | C33: 2 | D33: Mundane | E33: n/a | F33: Treasure | I33: Uberbeard | J33: 1
A34: Copper Chalice | B34: A small copper chalice with a silver filigree. | C34: 25 | D34: Mundane | E34: 1 | F34: Treasure | I34: DMG | J34: =IF(D34="Mundane", 1, IF(D34="Common", 2, IF(D34="Uncommon", 3, IF(D34="Rare", 4, IF(D34="Very Rare", 5, IF(D34="Legendary", 6, 100)))))) -> 1
A35: Crowbar | B35: Using a crowbar grants advantage to Strength checks where the crowbar’s leverage can be applied. | C35: 2 | D35: Mundane | E35: 5 | F35: Adventuring Gear | I35: PHB | J35: =IF(D35="Mundane", 1, IF(D35="Common", 2, IF(D35="Uncommon", 3, IF(D35="Rare", 4, IF(D35="Very Rare", 5, IF(D35="Legendary", 6, 100)))))) -> 1
A36: Crude Box | B36: A wooden box. Carved by someone who has had no formal training in woodworking, and it shows. | C36: 0.15 | D36: Mundane | E36: 1 | F36: Treasure | I36: Uberbeard | J36: =IF(D36="Mundane", 1, IF(D36="Common", 2, IF(D36="Uncommon", 3, IF(D36="Rare", 4, IF(D36="Very Rare", 5, IF(D36="Legendary", 6, 100)))))) -> 1
A37: Crude Holy Symbol | B37: A crudely carved wooden holy symbol. | C37: 0.5 | D37: Mundane | E37: 1 | F37: Treasure | I37: Uberbeard | J37: =IF(D37="Mundane", 1, IF(D37="Common", 2, IF(D37="Uncommon", 3, IF(D37="Rare", 4, IF(D37="Very Rare", 5, IF(D37="Legendary", 6, 100)))))) -> 1
A38: Crude Pipe | B38: A crudely carved wooden pipe. | C38: 0.15 | D38: Mundane | E38: n/a | F38: Treasure | I38: Uberbeard | J38: =IF(D38="Mundane", 1, IF(D38="Common", 2, IF(D38="Uncommon", 3, IF(D38="Rare", 4, IF(D38="Very Rare", 5, IF(D38="Legendary", 6, 100)))))) -> 1
A39: Curious Powder Box | B39: Metal box of unidentifiable powder. | C39: 0.5 | D39: Mundane | E39: 2 | F39: Treasure | I39: Unknown | J39: =IF(D39="Mundane", 1, IF(D39="Common", 2, IF(D39="Uncommon", 3, IF(D39="Rare", 4, IF(D39="Very Rare", 5, IF(D39="Legendary", 6, 100)))))) -> 1
A40: Dead Fey | B40: A long-dead fey, dried and petrified as a trophy and hanging from ceiling. | C40: 5 | D40: Mundane | E40: 120 | F40: Treasure | I40: Unknown | J40: =IF(D40="Mundane", 1, IF(D40="Common", 2, IF(D40="Uncommon", 3, IF(D40="Rare", 4, IF(D40="Very Rare", 5, IF(D40="Legendary", 6, 100)))))) -> 1
A41: Deer Bust | B41: The mounted head of a deer, it's impossibly massive horns have broken in places. | C41: 5 | D41: Mundane | E41: 7 | F41: Treasure | I41: Unknown | J41: =IF(D41="Mundane", 1, IF(D41="Common", 2, IF(D41="Uncommon", 3, IF(D41="Rare", 4, IF(D41="Very Rare", 5, IF(D41="Legendary", 6, 100)))))) -> 1
A42: Demon's Vale Wine | B42: A one-gallon cask of Demon’s Vale Wine; a fiery red wine known to be made from hot peppers. | C42: 10 | D42: Mundane | E42: 10 | F42: Treasure | I42: Unknown | J42: =IF(D42="Mundane", 1, IF(D42="Common", 2, IF(D42="Uncommon", 3, IF(D42="Rare", 4, IF(D42="Very Rare", 5, IF(D42="Legendary", 6, 100)))))) -> 1
A43: Dice (6 Sided) | B43: A six sided dice. Probably used in some silly tabletop game. | C43: 0.15 | D43: Mundane | E43: n/a | F43: Treasure | I43: Uberbeard | J43: =IF(D43="Mundane", 1, IF(D43="Common", 2, IF(D43="Uncommon", 3, IF(D43="Rare", 4, IF(D43="Very Rare", 5, IF(D43="Legendary", 6, 100)))))) -> 1
A44: Dinosaur Bacon | B44: 18 dried rashers of meat, possibly the largest rashers you have ever seen. They are wrapped in a sheep bladder cloth which has been labelled "THUNDERER MEAT" in large, rough handwriting. | C44: 10 | D44: Mundane | E44: n/a | F44: Treasure | I44: Uberbeard | J44: =IF(D44="Mundane", 1, IF(D44="Common", 2, IF(D44="Uncommon", 3, IF(D44="Rare", 4, IF(D44="Very Rare", 5, IF(D44="Legendary", 6, 100)))))) -> 1
A45: Dire Bat Wings | B45: Hanging from a drying rack are two large Dire Bat wings. It is unclear how long they have been seperated from the rest of the bat, but they are in good condition and could potentially be used as a crafting material. | C45: 2 | D45: Mundane | E45: 4 | F45: Treasure | I45: Uberbeard | J45: =IF(D45="Mundane", 1, IF(D45="Common", 2, IF(D45="Uncommon", 3, IF(D45="Rare", 4, IF(D45="Very Rare", 5, IF(D45="Legendary", 6, 100)))))) -> 1
A46: Disk of Balance | B46: A disk of finely polished stone. On one side, the Elvish rune for death is inscribed in blackest obsidian. Upon the other, the Dwarven rune for life is inscribed in the palest ivory. | C46: 4 | D46: Mundane | E46: n/a | F46: Treasure | I46: Unknown | J46: =IF(D46="Mundane", 1, IF(D46="Common", 2, IF(D46="Uncommon", 3, IF(D46="Rare", 4, IF(D46="Very Rare", 5, IF(D46="Legendary", 6, 100)))))) -> 1
A47: Weight Training Equipment | B47: The party finds a complete set of bronze and carved stone weight training equipment issued to the 4th army of some Ancient Empire. There is an inscription in one of the weights that reads "Dost thou even lift, brother?" | C47: 20 | D47: Mundane | E47: 200 | F47: Treasure | I47: Unknown | J47: =IF(D47="Mundane", 1, IF(D47="Common", 2, IF(D47="Uncommon", 3, IF(D47="Rare", 4, IF(D47="Very Rare", 5, IF(D47="Legendary", 6, 100)))))) -> 1
A48: Dried Flower | B48: A flower that has been dried out to preserve it. | C48: 0 | D48: Mundane | E48: n/a | F48: Treasure | I48: Uberbeard | J48: =IF(D48="Mundane", 1, IF(D48="Common", 2, IF(D48="Uncommon", 3, IF(D48="Rare", 4, IF(D48="Very Rare", 5, IF(D48="Legendary", 6, 100)))))) -> 1
A49: Dust Ruby | B49: A ruby the size of a man’s fist which sparkles and gleams with the promise of untold wealth in the faintest of lights, but which crumbles to dust upon the lightest touch. | C49: 0 | D49: Mundane | E49: n/a | F49: Treasure | I49: Unknown | J49: =IF(D49="Mundane", 1, IF(D49="Common", 2, IF(D49="Uncommon", 3, IF(D49="Rare", 4, IF(D49="Very Rare", 5, IF(D49="Legendary", 6, 100)))))) -> 1
A50: Electrum Bracer | B50: An archer’s bracer of leather and electrum. | C50: 2.5 | D50: Mundane | E50: 1 | F50: Armor | I50: PlatypusPal | J50: =IF(D50="Mundane", 1, IF(D50="Common", 2, IF(D50="Uncommon", 3, IF(D50="Rare", 4, IF(D50="Very Rare", 5, IF(D50="Legendary", 6, 100)))))) -> 1
A51: Leather Ball | B51: A leather ball stuffed with chicken feathers. On a DC 15 peception check the player can find an electrum ring amongst the feathers. | C51: 3.5 | D51: Mundane | E51: n/a | F51: Treasure | I51: Uberbeard | J51: =IF(D51="Mundane", 1, IF(D51="Common", 2, IF(D51="Uncommon", 3, IF(D51="Rare", 4, IF(D51="Very Rare", 5, IF(D51="Legendary", 6, 100)))))) -> 1
A52: Empty Vial | B52: An empty vial, just waiting to be filled with something more valuable than itself. | C52: 0.35 | D52: Mundane | E52: n/a | F52: Treasure | I52: Uberbeard | J52: =IF(D52="Mundane", 1, IF(D52="Common", 2, IF(D52="Uncommon", 3, IF(D52="Rare", 4, IF(D52="Very Rare", 5, IF(D52="Legendary", 6, 100)))))) -> 1
A53: Eye Agate Gem | B53: This simple agate gem has translucent circles of white dotted around its surface which bring to mind the image of an eye. | C53: 10 | D53: Mundane | E53: n/a | F53: Treasure | I53: DMG | J53: =IF(D53="Mundane", 1, IF(D53="Common", 2, IF(D53="Uncommon", 3, IF(D53="Rare", 4, IF(D53="Very Rare", 5, IF(D53="Legendary", 6, 100)))))) -> 1
A54: Fat Cat Statue | B54: A life sized copper statue of a fat cat with amber eyes that purrs when stroked. Curiously, it does not detect as magic. | C54: 5 | D54: Mundane | E54: 2 | F54: Treasure | I54: Unknown | J54: =IF(D54="Mundane", 1, IF(D54="Common", 2, IF(D54="Uncommon", 3, IF(D54="Rare", 4, IF(D54="Very Rare", 5, IF(D54="Legendary", 6, 100)))))) -> 1
A55: Fine Cheese | B55: A 5’ diameter wheel of fine, aged cheese | C55: 0.5 | D55: Mundane | E55: 4 | F55: Treasure | I55: Uberbeard | J55: =IF(D55="Mundane", 1, IF(D55="Common", 2, IF(D55="Uncommon", 3, IF(D55="Rare", 4, IF(D55="Very Rare", 5, IF(D55="Legendary", 6, 100)))))) -> 1
A56: Fishing Tackle | B56: Useful for catching fish. | C56: 1 | D56: Mundane | E56: n/a | F56: Adventuring Gear | I56: PHB | J56: =IF(D56="Mundane", 1, IF(D56="Common", 2, IF(D56="Uncommon", 3, IF(D56="Rare", 4, IF(D56="Very Rare", 5, IF(D56="Legendary", 6, 100)))))) -> 1
A57: Flesh Shield | B57: A small wooden shield bound in human skin bearing a tattoo that appears to be some sort of map. The skin is held in place with a rim of beaten copper. | C57: 7 | D57: Mundane | E57: 6 | F57: Armor | G57: Provides +2 AC | I57: Unknown | J57: =IF(D57="Mundane", 1, IF(D57="Common", 2, IF(D57="Uncommon", 3, IF(D57="Rare", 4, IF(D57="Very Rare", 5, IF(D57="Legendary", 6, 100)))))) -> 1
A58: Flint & Steel | B58: A carved steel striker and a piece of shaped flint that allows the user to start a fire. | C58: 0.3 | D58: Mundane | E58: n/a | F58: Treasure | I58: PHB | J58: =IF(D58="Mundane", 1, IF(D58="Common", 2, IF(D58="Uncommon", 3, IF(D58="Rare", 4, IF(D58="Very Rare", 5, IF(D58="Legendary", 6, 100)))))) -> 1
A59: Fool's Gold | B59: A handheld water pan with a number of chunks of pyrite in it, otherwise known as "Fool's Gold". You might be able to convince someone that these nuggets are real gold, but not for very long. | C59: 0.5 | D59: Mundane | E59: 1 | F59: Treasure | I59: Uberbeard | J59: =IF(D59="Mundane", 1, IF(D59="Common", 2, IF(D59="Uncommon", 3, IF(D59="Rare", 4, IF(D59="Very Rare", 5, IF(D59="Legendary", 6, 100)))))) -> 1
A60: Fragrant Torches | B60: A bag containing 1d8 torches infused with pleasant fragrances. This may have been owned by a tanner, to cover the overwhelming stench of tannin that is used in the leathermaking process. | C60: 4 | D60: Mundane | E60: 2 | F60: Treasure | I60: Uberbeard | J60: =IF(D60="Mundane", 1, IF(D60="Common", 2, IF(D60="Uncommon", 3, IF(D60="Rare", 4, IF(D60="Very Rare", 5, IF(D60="Legendary", 6, 100)))))) -> 1
A61: Frolee's Guide to Follicle Perfection | B61: A wizard called Frolee appears to have mass produced a five page guide to mustaches and beards. It has a unique, hairy cover made out of bearskin. | C61: 2 | D61: Mundane | E61: 1 | F61: Book | H61: Language: Common | I61: PlatypusPal | J61: =IF(D61="Mundane", 1, IF(D61="Common", 2, IF(D61="Uncommon", 3, IF(D61="Rare", 4, IF(D61="Very Rare", 5, IF(D61="Legendary", 6, 100)))))) -> 1
A62: Garlic | B62: A wreath of eight garlic buds. | C62: 0.2 | D62: Mundane | E62: n/a | F62: Treasure | I62: Uberbeard | J62: =IF(D62="Mundane", 1, IF(D62="Common", 2, IF(D62="Uncommon", 3, IF(D62="Rare", 4, IF(D62="Very Rare", 5, IF(D62="Legendary", 6, 100)))))) -> 1
A63: Gem | B63: A teal gem. | C63: 1 | D63: Mundane | E63: n/a | F63: Treasure | I63: Uberbeard | J63: =IF(D63="Mundane", 1, IF(D63="Common", 2, IF(D63="Uncommon", 3, IF(D63="Rare", 4, IF(D63="Very Rare", 5, IF(D63="Legendary", 6, 100)))))) -> 1
A64: Gem of Azurite | B64: A small Azurite gem. It is opaque and a deep mottled blue in colour. | C64: 10 | D64: Mundane | E64: n/a | F64: Treasure | I64: DMG | J64: =IF(D64="Mundane", 1, IF(D64="Common", 2, IF(D64="Uncommon", 3, IF(D64="Rare", 4, IF(D64="Very Rare", 5, IF(D64="Legendary", 6, 100)))))) -> 1
A65: Glass Sphere | B65: A 14 inch diameter sealed glass sphere containing water and an ornamental fish. | C65: 3 | D65: Mundane | E65: 8 | F65: Treasure | I65: Uberbeard | J65: =IF(D65="Mundane", 1, IF(D65="Common", 2, IF(D65="Uncommon", 3, IF(D65="Rare", 4, IF(D65="Very Rare", 5, IF(D65="Legendary", 6, 100)))))) -> 1
A66: Glittering Glass | B66: A sparkling handful of raw gems. | C66: 0.01 | D66: Mundane | E66: n/a | F66: Treasure | G66: These convincing rocks are actually made of a river-tumbled glassy stone that is said to form from the aftermath of elemental turmoil. | I66: /u/gimme_some_sunshine | J66: =IF(D66="Mundane", 1, IF(D66="Common", 2, IF(D66="Uncommon", 3, IF(D66="Rare", 4, IF(D66="Very Rare", 5, IF(D66="Legendary", 6, 100)))))) -> 1
A67: Glitternight Dust | B67: This is a tiny jar of glitternight dust. (a narcotic) | C67: 3 | D67: Mundane | E67: 1 | F67: Treasure | J67: =IF(D67="Mundane", 1, IF(D67="Common", 2, IF(D67="Uncommon", 3, IF(D67="Rare", 4, IF(D67="Very Rare", 5, IF(D67="Legendary", 6, 100)))))) -> 1
A68: Glow Stone | B68: A small green stone that gives off a feint light that's practically imperceptable in anything other than pitch black darkness. It could be used as a marker or a light source in a pinch. | C68: 2 | D68: Mundane | E68: n/a | F68: Treasure | G68: Provides dim-light for a 5 foot radius. | J68: =IF(D68="Mundane", 1, IF(D68="Common", 2, IF(D68="Uncommon", 3, IF(D68="Rare", 4, IF(D68="Very Rare", 5, IF(D68="Legendary", 6, 100)))))) -> 1
A69: Goat Jerky | B69: A pound of goat jerky. | C69: 0.2 | D69: Mundane | E69: 1 | F69: Treasure | J69: =IF(D69="Mundane", 1, IF(D69="Common", 2, IF(D69="Uncommon", 3, IF(D69="Rare", 4, IF(D69="Very Rare", 5, IF(D69="Legendary", 6, 100)))))) -> 1
A70: Gold Bracelet | B70: A small gold bracelet. It's design is plain so as to be appropriate for anyone. | C70: 25 | D70: Mundane | E70: n/a | F70: Treasure | I70: DMG | J70: =IF(D70="Mundane", 1, IF(D70="Common", 2, IF(D70="Uncommon", 3, IF(D70="Rare", 4, IF(D70="Very Rare", 5, IF(D70="Legendary", 6, 100)))))) -> 1
A71: Gold Locket | B71: A charming golden locket with a painted portrait inside. | C71: 25 | D71: Mundane | E71: n/a | F71: Treasure | I71: DMG | J71: =IF(D71="Mundane", 1, IF(D71="Common", 2, IF(D71="Uncommon", 3, IF(D71="Rare", 4, IF(D71="Very Rare", 5, IF(D71="Legendary", 6, 100)))))) -> 1
A72: Hammer | B72: A crosspeen hammer forged from steel. It has a gently crowned flat face that has been hardened and tempered for toughness. The handle is hand carved ash, flame treated and oiled. | C72: 1 | D72: Mundane | E72: 3 | F72: Adventuring Gear | I72: PHB | J72: =IF(D72="Mundane", 1, IF(D72="Common", 2, IF(D72="Uncommon", 3, IF(D72="Rare", 4, IF(D72="Very Rare", 5, IF(D72="Legendary", 6, 100)))))) -> 1
A73: Hand Mirror | C73: 2 | D73: Mundane | E73: n/a | F73: Treasure | I73: Uberbeard | J73: =IF(D73="Mundane", 1, IF(D73="Common", 2, IF(D73="Uncommon", 3, IF(D73="Rare", 4, IF(D73="Very Rare", 5, IF(D73="Legendary", 6, 100)))))) -> 1
A74: Hematite | B74: A rather dull gray-black hematite gem with the remains of a necklace fasten on its back. | C74: 10 | D74: Mundane | E74: n/a | F74: Treasure | I74: DMG | J74: =IF(D74="Mundane", 1, IF(D74="Common", 2, IF(D74="Uncommon", 3, IF(D74="Rare", 4, IF(D74="Very Rare", 5, IF(D74="Legendary", 6, 100)))))) -> 1
A75: Holy Bones | B75: A reliquary containing the bones of an ancient holy man | C75: 0 | D75: Mundane | E75: 2 | F75: Treasure | J75: =IF(D75="Mundane", 1, IF(D75="Common", 2, IF(D75="Uncommon", 3, IF(D75="Rare", 4, IF(D75="Very Rare", 5, IF(D75="Legendary", 6, 100)))))) -> 1
A76: Holy Book | B76: An old tome, written for the clergy of Pelor. It has a stiff leather dust jacket which has been worn down on the spine and a broken clasp once used to attach a chain | C76: 4 | D76: Mundane | E76: 1 | F76: Book | H76: Language: Common | I76: Uberbeard | J76: =IF(D76="Mundane", 1, IF(D76="Common", 2, IF(D76="Uncommon", 3, IF(D76="Rare", 4, IF(D76="Very Rare", 5, IF(D76="Legendary", 6, 100)))))) -> 1
A77: Holy Ice Symbol | B77: An ornate block of ice carved into an ancient holy symbol. The carving has a subtle taint of magic to it, but it's not exactly clear what prevents it from melting. | C77: 400 | D77: Uncommon | E77: 2 | F77: Treasure | J77: =IF(D77="Mundane", 1, IF(D77="Common", 2, IF(D77="Uncommon", 3, IF(D77="Rare", 4, IF(D77="Very Rare", 5, IF(D77="Legendary", 6, 100)))))) -> 3
A78: Holy Symbol | B78: A wooden holy symbol. | C78: 0.25 | D78: Mundane | E78: n/a | F78: Adventuring Gear | I78: Uberbeard | J78: =IF(D78="Mundane", 1, IF(D78="Common", 2, IF(D78="Uncommon", 3, IF(D78="Rare", 4, IF(D78="Very Rare", 5, IF(D78="Legendary", 6, 100)))))) -> 1
A79: Honey | B79: A quart of honey. | C79: 1 | D79: Mundane | E79: n/a | F79: Treasure | J79: =IF(D79="Mundane", 1, IF(D79="Common", 2, IF(D79="Uncommon", 3, IF(D79="Rare", 4, IF(D79="Very Rare", 5, IF(D79="Legendary", 6, 100)))))) -> 1
A80: Honeysuckle Potion | B80: A small, crystal vial of a clear, viscous liquid that smells strongly of honeysuckle. | C80: 4 | D80: Mundane | E80: n/a | F80: Potion | G80: Drinking this potion will heal a character 1d4 - 1 health. | I80: Uberbeard | J80: =IF(D80="Mundane", 1, IF(D80="Common", 2, IF(D80="Uncommon", 3, IF(D80="Rare", 4, IF(D80="Very Rare", 5, IF(D80="Legendary", 6, 100)))))) -> 1
A81: Hope Chest | B81: A delicately carved hope chest of polished cherry wood. The box contains nothing but a remarkably fine, gray sand drawn from some unknown locale. Beneath the new moon, this sand glows a faint blue. | C81: 10 | D81: Mundane | E81: 30 | F81: Treasure | J81: =IF(D81="Mundane", 1, IF(D81="Common", 2, IF(D81="Uncommon", 3, IF(D81="Rare", 4, IF(D81="Very Rare", 5, IF(D81="Legendary", 6, 100)))))) -> 1
A82: Inhalation Herbs & Essences | B82: Inhalation herbs & essences provide natural healing remedies for all manner of symptoms such as headaches, colds and flu. | C82: 0.2 | D82: Mundane | E82: 2 | F82: Treasure | J82: =IF(D82="Mundane", 1, IF(D82="Common", 2, IF(D82="Uncommon", 3, IF(D82="Rare", 4, IF(D82="Very Rare", 5, IF(D82="Legendary", 6, 100)))))) -> 1
A83: Ink | B83: A vial of black ink, for use with a quill. | C83: 0.6 | D83: Mundane | E83: n/a | F83: Treasure | G83: When unstoppered underwater, this item causes an inky cloud to fill a 10′ cubic area which lasts for the duration of the room. It effectively renders all characters and monsters in the area obscured from ranged attacks. | I83: Uberbeard | J83: =IF(D83="Mundane", 1, IF(D83="Common", 2, IF(D83="Uncommon", 3, IF(D83="Rare", 4, IF(D83="Very Rare", 5, IF(D83="Legendary", 6, 100)))))) -> 1
A84: Iron Buckle | B84: An iron belt buckle that's beginning to rust. | C84: 0.03 | D84: Mundane | E84: n/a | F84: Treasure | I84: Uberbeard | J84: =IF(D84="Mundane", 1, IF(D84="Common", 2, IF(D84="Uncommon", 3, IF(D84="Rare", 4, IF(D84="Very Rare", 5, IF(D84="Legendary", 6, 100)))))) -> 1
A85: Iron Earring | B85: An iron earring. Missing it's twin. | C85: 0.1 | D85: Mundane | E85: n/a | F85: Treasure | I85: Uberbeard | J85: =IF(D85="Mundane", 1, IF(D85="Common", 2, IF(D85="Uncommon", 3, IF(D85="Rare", 4, IF(D85="Very Rare", 5, IF(D85="Legendary", 6, 100)))))) -> 1
A86: Iron Nail | B86: A large iron nail, useful for fixing things together. | C86: 0.03 | D86: Mundane | E86: n/a | F86: Treasure | I86: Uberbeard | J86: =IF(D86="Mundane", 1, IF(D86="Common", 2, IF(D86="Uncommon", 3, IF(D86="Rare", 4, IF(D86="Very Rare", 5, IF(D86="Legendary", 6, 100)))))) -> 1
A87: Iron Spike | B87: A large iron spike, useful for fixing heavy items together. | C87: 0.35 | D87: Mundane | E87: 1 | F87: Treasure | I87: Uberbeard | J87: =IF(D87="Mundane", 1, IF(D87="Common", 2, IF(D87="Uncommon", 3, IF(D87="Rare", 4, IF(D87="Very Rare", 5, IF(D87="Legendary", 6, 100)))))) -> 1
A88: Iron Torc | B88: An iron torc with six small silver figurines: A hare, a horse, a spear, a wolf’s head, a simple circle, and an oak tree. | C88: 9 | D88: Mundane | E88: n/a | F88: Treasure | J88: =IF(D88="Mundane", 1, IF(D88="Common", 2, IF(D88="Uncommon", 3, IF(D88="Rare", 4, IF(D88="Very Rare", 5, IF(D88="Legendary", 6, 100)))))) -> 1
A89: Ivory Peg Leg | B89: Whale ivory leg prosthetic | C89: 5 | D89: Mundane | E89: 2 | F89: Treasure | J89: =IF(D89="Mundane", 1, IF(D89="Common", 2, IF(D89="Uncommon", 3, IF(D89="Rare", 4, IF(D89="Very Rare", 5, IF(D89="Legendary", 6, 100)))))) -> 1
A90: Jar o' Eyeballs | B90: A jar containing six eyeballs (2 human, 1 goblin, 1 ogre, 1 worg, and 1 hawk) in a clear liquid. | C90: 2 | D90: Mundane | E90: 1 | F90: Treasure | J90: =IF(D90="Mundane", 1, IF(D90="Common", 2, IF(D90="Uncommon", 3, IF(D90="Rare", 4, IF(D90="Very Rare", 5, IF(D90="Legendary", 6, 100)))))) -> 1
A91: Jerked Meats | B91: ½ of jerked meat | C91: 0.1 | D91: Mundane | E91: 0.5 | F91: Treasure | J91: =IF(D91="Mundane", 1, IF(D91="Common", 2, IF(D91="Uncommon", 3, IF(D91="Rare", 4, IF(D91="Very Rare", 5, IF(D91="Legendary", 6, 100)))))) -> 1
A92: Keg o' Nails | B92: A 35 lb keg of iron nails | C92: 2 | D92: Mundane | E92: 35 | F92: Treasure | J92: =IF(D92="Mundane", 1, IF(D92="Common", 2, IF(D92="Uncommon", 3, IF(D92="Rare", 4, IF(D92="Very Rare", 5, IF(D92="Legendary", 6, 100)))))) -> 1
A93: Knee Breeches | B93: A pair of bear fur knee breeches, slightly worn from having been used when horse riding. | C93: 1 | D93: Mundane | E93: 2 | F93: Treasure | J93: =IF(D93="Mundane", 1, IF(D93="Common", 2, IF(D93="Uncommon", 3, IF(D93="Rare", 4, IF(D93="Very Rare", 5, IF(D93="Legendary", 6, 100)))))) -> 1
A94: Lantern | B94: A slightly rusty old lantern with a glass casing. | D94: Mundane | E94: 1 | F94: Adventuring Gear | G94: A Lantern provides bright light within a radius of 10 squares. The light lasts 8 hours per pint of oil. | I94: Uberbeard | J94: =IF(D94="Mundane", 1, IF(D94="Common", 2, IF(D94="Uncommon", 3, IF(D94="Rare", 4, IF(D94="Very Rare", 5, IF(D94="Legendary", 6, 100)))))) -> 1
A95: Lapis Lazuli Gem | B95: A gem of lapis lazuli, dark blue in colour with light yellow flecks. | C95: 10 | D95: Mundane | E95: n/a | F95: Treasure | I95: DMG | J95: =IF(D95="Mundane", 1, IF(D95="Common", 2, IF(D95="Uncommon", 3, IF(D95="Rare", 4, IF(D95="Very Rare", 5, IF(D95="Legendary", 6, 100)))))) -> 1
A96: Large Pile of Coal | B96: A large pile of coal. Two small, rough diamonds are hidden near the bottom. (20gp, 25 gp) | D96: Mundane | F96: Treasure | J96: =IF(D96="Mundane", 1, IF(D96="Common", 2, IF(D96="Uncommon", 3, IF(D96="Rare", 4, IF(D96="Very Rare", 5, IF(D96="Legendary", 6, 100)))))) -> 1
A97: Lead Coins | B97: Satchel of gold painted lead coins. | C97: 0.1 | D97: Mundane | E97: 1 | F97: Treasure | J97: =IF(D97="Mundane", 1, IF(D97="Common", 2, IF(D97="Uncommon", 3, IF(D97="Rare", 4, IF(D97="Very Rare", 5, IF(D97="Legendary", 6, 100)))))) -> 1
A98: Leather Quiver | D98: Mundane | E98: 4 | F98: Treasure | I98: Uberbeard | J98: =IF(D98="Mundane", 1, IF(D98="Common", 2, IF(D98="Uncommon", 3, IF(D98="Rare", 4, IF(D98="Very Rare", 5, IF(D98="Legendary", 6, 100)))))) -> 1
A99: Leather Satchel | D99: Mundane | E99: 1 | F99: Treasure | I99: Uberbeard | J99: =IF(D99="Mundane", 1, IF(D99="Common", 2, IF(D99="Uncommon", 3, IF(D99="Rare", 4, IF(D99="Very Rare", 5, IF(D99="Legendary", 6, 100)))))) -> 1
A100: Little Riding Hood | B100: A bright red hooded cape sized for a child, spattered with dried blood. | C100: 1 | D100: Mundane | E100: 1 | F100: Treasure | J100: =IF(D100="Mundane", 1, IF(D100="Common", 2, IF(D100="Uncommon", 3, IF(D100="Rare", 4, IF(D100="Very Rare", 5, IF(D100="Legendary", 6, 100)))))) -> 1
...

Sheet Logic
B2: Rarity | C2: Item Count
B3: Mundane | C3: =COUNTIF('Dungeon Loot'!F2:Z1004, "=1") -> 186
B4: Common | C4: =COUNTIF('Dungeon Loot'!F2:Z1004, "=2") -> 274
B5: Uncommon | C5: =COUNTIF('Dungeon Loot'!F3:Z1005, "=3") -> 215
B6: Rare | C6: =COUNTIF('Dungeon Loot'!F4:Z1006, "=4") -> 192
B7: Very Rare | C7: =COUNTIF('Dungeon Loot'!F5:Z1007, "=5") -> 82
B8: Legendary | C8: =COUNTIF('Dungeon Loot'!F6:Z1008, "=6") -> 36

Sheet Form Submissions
A1: Timestamp | B1: Name | C1: Description | D1: Estimated Value | E1: Rarity | F1: Weight | G1: Category | H1: Properties | I1: Requirements | J1: Author
A2: 42696.96 | B2: Banshee Spirit Dagger | C2: Despite appearing to be a normal dagger, even those not able to recognise the presence of magic can tell that there is something imbued in the unassuming metal hilt and blade. When appraised it transpires that this blade was buried with a banshee and it's spirit has somehow been absorbed. Now whomever uses the dagger carries the risk that its spirit will be unleashed. | D2: 2000 | E2: Rare | F2: 2 lb. | G2: Weapon | H2: On a critical hit, it'll scream like her. It hasn't happened yet, but I imagine it'll either force the target to make a will save or be feared, or possibly drop to zero hit points. | J2: /u/Silanoch
A3: 42588.682 | B3: Eternity Armor | C3: Nigh-unbreakable golemsteel armor enchanted to withstand nearly any strike. If a ranged attack targets a friendly creature besides yourself within five feet radius, you can move them and take the shot to negate the damage and effects instead; if they are within a 10 feet radius, use your reaction. | E3: Legendary | F3: 80 | G3: Armor | H3: Heavy Armor| AC 20 | Str 20 | Stealth: Disadvantage | | J3: u/giratina2648
A4: 42588.643 | B4: Ring of Dubious Might | C4: A silver ring, encrusted with a small topaz. Upon wearing it on their finger, the wearer feels incredibly strong and confident. However, entering combat, their confidence immediately dissipates, leaving them terrified. | D4: 20gp | E4: Uncommon | F4: n/a | G4: Ring | J4: Jacos
A5: 42588.624 | B5: Cloak of the Shadow General | C5: A commanding cloak of authority, used to hide whole legions of armies against the Starwizards of the astral planes. | E5: Legendary | F5: 0 | G5: Wondrous Item | H5: 1/ Day: Creatures within a 30 feet radius, including the user, are granted the effects of greater invisibility, and cannot be detected by Truesight and other means of reveal, e.g. Mordenkainen's Faithful Hound. Charges are restored at dusk. | J5: u/giratina2648
A6: 42588.582 | B6: The Eye of Far Seeing (requires attunement) | C6: This legendary eyeball, said to have once been that of a gynosphinx, has the capability to scry at a radius of around 1000 miles. To use it, one must attune to it and to do so, one must gouge out one of their own eyes and replace it with the Eye of Far Seeing (similar to the eye of vecna). | D6: 30,000 gp | E6: Legendary | F6: 1-2 grams (sorry, I'm a metric guy) | G6: Wondrous Item | H6: Inserting this eye into one of your own eyes lots gives the ability to scry at will twice (or thrice) a day. If it is used more than that, your vision in that eye will start to fade and you will suffer exhaustion. | J6: J
A7: 42588.551 | B7: Animated Shield | C7: While holding this shield, you can speak its command word as a bonus action to cause it to animate. The shield leaps into the air and hovers in your space to protect you as if you were wielding it, leaving your hands free. The shield remains animated for 1 minute, until you use a bonus action to end this effect, or until you are incapacitated or die, at which point the shield falls to the ground or into your hand if you have one free. | E7: Very Rare | G7: Armor | H7: Requires Attunement | J7: DMG
A8: 42759.109 | B8: Stern Sword of Grammar Correction | C8: A dull, rather drab looking rapier inhabited with the intelligence of a hyper-particular grammarian. | E8: Very Rare | G8: Weapon | H8: Acts as a +1 sword vs any creature speaking with poor grammar construction. On a successful hit, the creature must save or begin using immaculate grammar (spelling gets a bump too), after which the sword attacks the creature as a mundane weapon. Shocks the wielder for 1 hp damage each time he or she uses poor grammar. | J8: Jeff C
A9: 42772.988 | B9: Boots of Feral Leaping | C9: Plain leather boots, tattered and worn, but glistening with a soft white light similar to the sunlight reflecting off freshly fallen snow. | D9: 1500 | E9: Rare | F9: 2 | G9: Armor | H9: When you wear these boots you can instill your leaps with incredible bursts of power. As a bonus action, you can attempt to leap. Make a DC16 Strength check: if you are successful, you can leap either 15 feet vertically or 20 feet horizontally. On a failure, you are knocked prone where you stand. | J9: /u/gimme_some_sunshine via Matt Mercer
A10: 42775.006 | B10: Ring Mail of Three Wishes | C10: This armor is Leather Armor with heavy rings sewn into it. The rings help reinforce the armor against blows from swords and axes. Three rings across the chest are made of brilliant gold that sheds dim light similar to daybreak. | D10: 1500 | E10: Rare | F10: 40 | G10: Armor | H10: When you are hit by a melee or ranged attack while wearing this armor, you can use your reaction to wish that you hadn't been hit. The attack deals no damage, but the armor class provided by the armor decreases by 1. After the third wish, the armor's rings vanish and it becomes nonmagical leather armor. | I10: Requires Attunement | J10: /u/gimme_some_sunshine
A11: 42775.008 | B11: Necromancer's Saddle | C11: Black leather saddle with streaks of red through the leather itself. A small amount of black smoke emanates from the saddle when it is holding still. | D11: 2000 | E11: Rare | F11: 30 | G11: Wondrous Item | H11: You can use an action to place this saddle on the corpse or skeleton of a Large creature and animate it as an undead mount. The undead creature's bones shift as necessary to create something similar to a warhorse skeleton (MM 273), which follows your mental commands as long as you are riding it. The effect lasts until you remove the saddle, or until the next dawn. When the effect ends, the undead creature crumbles into dust. | J11: /u/gimme_some_sunshine
A12: 42978.414 | B12: Sword of Bleeding | C12: A sharp one-sided blade that is slightly curved. | E12: Rare | G12: Weapon | H12: The creature must a Constitution saving throw of 14 or take an addition 1d6. The creature makes this check every turn until succeeded | J12: Brendan M
A13: 42978.414 | B13: Shield of Bashing | C13: A tough metal shield with a large stud in the center. | E13: Rare | G13: Weapon | H13: When running to a target from at least 20 feet. The target must make a Constitution saving throw of 14 or be knocked prone. Following attacks would then have advantage. | J13: Brendan M
A14: 42978.415 | B14: Crate of Chaos Mushrooms | C14: This wooden crate is about 60cm by 60cm by 40cm, with 'Chaos Mushrooms' burned into the lid in Sylvan. It fizzes with a faint magical aura, and smells delicious | D14: 2000 | E14: Rare | F14: 30lbs | G14: Treasure | H14: The box contains 1d10+4 'Chaos Mushrooms', which are considered a delecacy at Fey dinner parties. If a creature eats one of the Chaos Mushrooms, they must roll on the Wild Magic Surge table (PHB, p104) and are subject to the result. Each mushroom eaten requires a seperate roll. | J14: /u/Ragatan
A15: 43187.792 | B15: Spire of the Manticore | C15: You gain a +1 bonus to attack and damage rolls with this magical weapon, and it deals an additional 1d8 poison damage. The damage increases by 1d8 if the target is a Monstrosity or Beast. This weapon has 7 spikes hidden within the Barb at the end of the pike. As a ranged attack, you can launch a single spike at a target, each having a range of 100/200 ft. Each of these spikes deal 1d8 piercing damage. Every Morning at dawn, this weapon regrows all of it's spikes. | D15: 5,000gp | E15: Rare | F15: 18 | G15: Weapon | H15: Heavy, Reach, Two-Handed | I15: Requires Attunement | J15: Fin Fen
A16: 43187.795 | B16: Chimera's Mantel | C16: This Cloak is woven together from the fur of a lion and goat over the skin of a serpent. It bears the emblem of house Chimera. While wearing this cloak and attuned to it, you gain fire resistance. In addition you can use your action to exhale fire in a 15-foot cone. Each creature in that area must make a DC 15 Dexterity saving throw, taking 7d8 fire damage on a failed save, or half as much damage on a successful one. Once you use this ability, you cannot do so again until you take a short rest. | D16: 5,000gp | E16: Rare | F16: 1 | G16: Wondrous Item | I16: Requires Attunement | J16: Fin Fen
A17: 43187.8 | B17: Necklace of the Fang PAct | C17: This fiber necklace contains beads that separate several teeth from a variety of creatures. All together, it can support up to 7 teeth. While wearing this amulet, you can use an action to sap the remaining essence from a creature that has been brought to 0 hit points. Doing so turns the creature's flesh into ash and forges its life force into a tooth appropriate for its type which magically binds itself to the amulet. Each tooth has a type and a property. As a ritual, you can expend one tooth to gain its property for 24 hours or until a new ritual has been performed. Constructs, Oozes, and Plants are unaffected by this item. Undead whose essence you sap grant you a tooth with the type that it possessed in life rather than undeath. *Aberrations: You can magically transmit simple messages and images to any creature within 120 ft. that can understand a Language. This form of telepathy doesn't allow the receiving creature to telepathically respond. *Beasts: Your hit point maximum increases by an amount equal to twice your level. *Celestials: As an action, you can touch a target and remove any curse, disease, poison, blindness, or deafness condition. *Dragons: Your breath weapon gains a recharge of 6 and its damage die is increased to d8. *Elemental: You choose acid, cold, fire, lightning, poison, or thunder and gain resistance to that element. *Fey: Touching a creature, you magically know the creature's current emotional state. If the target fails a Charisma saving throw, you also know the creature's alignment. Celestials, Fiends, and Undead automatically fail the saving throw. *Fiends: You gain advantage on saving throws against Spells and other magical effects. *Giants: Your Strength score is 21. This property has no effect on you if your Strength is already 21 or higher without this necklace. *Humanoids: You become proficient in any two skills. Your proficiency bonus is doubled for any ability check you make that uses either of the chosen proficiencies. *Monstrosities: You gain Darkvision 60 Ft. and Tremorsense 60 Ft. In addition, you gain a keen sense of hearing and smelling which grants you advantage on Wisdom (Perception) checks that rely on hearing or smell. | D17: 25,000gp | E17: Very Rare | F17: 1 | G17: Wondrous Item | I17: Requires Attunement | J17: Fin Fen
A18: 43187.82 | B18: Remnant | C18: "The handle was made of black leathers which connected two chains down to the head of a cylinder-shaped flail head. The head was like a cage that had interlocking strips of steel with spikes pointing outwards at every link. Inside, it contained a brilliant blue light that hummed which grew with intensity when spun." | D18: 40000 | E18: Very Rare | F18: 4 | G18: Weapon | H18: You have a + 1 bonus to attack and damage rolls made with this magic weapon. The Flail Head sheds dim light in a 10-foot radius. When you roll a 20 on a weapon attack with Remnant, you may conjure forth a frost giant from a mist that flows out from the blue light in the head of this weapon. The creature appears in the same space you are in, using its height to leave the user room to move. If he cannot fit in the space, the creature refuses to be summoned. After your turn ends, The creature immediately takes it's initiative. The creature hears what commands you have, but acts on it's own and is capable of making it's own decisions. After it's turn is over, the creature remains until the start of your next turn before returning to mist and binding itself to Remnant once more. Once this ability is used, it cannot be used again until you complete a short rest. | I18: Requires Attunement | J18: Fin Fen
A19: 43187.821 | B19: Necklace of the Fang Pact | C19: This fiber necklace contains beads that separate several teeth from a variety of creatures. All together, it can support up to 7 teeth. | D19: 5,000gp | E19: Very Rare | G19: Wondrous Item | H19: While wearing this amulet, you can use an action to sap the remaining essence from a creature that has been brought to 0 hit points. Doing so turns the creature's flesh into ash and forges its life force into a tooth appropriate for its type which magically binds itself to the amulet. Each tooth has a type and a property. As a ritual, you can expend one tooth to gain its property for 24 hours or until a new ritual has been performed. Constructs, Oozes, and Plants are unaffected by this item. Undead whose essence you sap grant you a tooth with the type that it possessed in life rather than undeath. *Aberrations: You can magically transmit simple messages and images to any creature within 120 ft. that can understand a Language. This form of telepathy doesn't allow the receiving creature to telepathically respond. *Beasts: Your hit point maximum increases by an amount equal to twice your level. *Celestials: As an action, you can touch a target and remove any curse, disease, poison, blindness, or deafness condition. *Dragons: Your breath weapon gains a recharge of 6 and its damage die is increased to d8. *Elemental: You choose acid, cold, fire, lightning, poison, or thunder and gain resistance to that element. *Fey: Touching a creature, you magically know the creature's current emotional state. If the target fails a Charisma saving throw, you also know the creature's alignment. Celestials, Fiends, and Undead automatically fail the saving throw. *Fiends: You gain advantage on saving throws against Spells and other magical effects. *Giants: Your Strength score is 21. This property has no effect on you if your Strength is already 21 or higher without this necklace. *Humanoids: You become proficient in any two skills. Your proficiency bonus is doubled for any ability check you make that uses either of the chosen proficiencies. *Monstrosities: You gain Darkvision 60 Ft. and Tremorsense 60 Ft. In addition, you gain a keen sense of hearing and smelling which grants you advantage on Wisdom (Perception) checks that rely on hearing or smell. | I19: Requires Attunement | J19: Fin Fen
A20: 43187.877 | B20: Cloak of Partial Shadow | C20: A normal looking black cloak with a high collar. When activated it gives off small puffs of black smoke that help obscure the wearer. | D20: 250 gp | E20: Uncommon | F20: 5 lbs | G20: Armor | H20: Speak the command word to activate the cloak and receive advantage on your next stealth roll. The wearer can only benefit from the effect once. It lasts for up to 6 seconds. | J20: AdamLapka
A21: 43477.426 | B21: Psyche of Strife | C21: A tall mirror in ornate silvery frame with perfectly reflecting surface. The ornaments depicting faceless humanoids locked in battle. | D21: 15.000gp | E21: Very Rare | F21: 70 lbs | G21: Wondrous Item | H21: Anyone who looks into the mirror will see their own perfect reflection. However, when the first character takes a glimpse on someone else's image, they will see a horrifying visage of a powerful monster (lich, mind flayer, etc.), likely to be found in the complex where the Psyche is located. This effect is commanded by a demonic intelligence imprisoned in the shiny surface, and will occur in a manner to cause maximum confusion, mistrust and likely infighting to bands of adventurers. It's very easy to shatter the mirror, however all the fragments will have the same tendency to occasionally show your best friend as a rotting undead - only to you. | J21: Rutin75
A22: 43478.246 | B22: adf | C22: Test | D22: 30 | E22: Uncommon | G22: Book
A23: 43730.685 | B23: Frosted Dagger | C23: A simple dagger with a blue hilt. The blade is almost always covered in frost. Does 1d4 +2 cold damage. | D23: 25gp | E23: Common | F23: 1 lb | G23: Weapon | H23: +2 cold damage | J23: Arctiquaza
A24: 43761.789 | B24: Exceptionally Roguish Hat | C24: A wide, leather hat, garnished with gold-inlaid thread and exotic bird feathers. Very Vogue. | D24: 1050 | E24: Rare | F24: 1 lb | G24: Treasure | H24: Putting the hat on causes the wearer to gain 2 CHA and becomes bound to the hat's thrall. The wearer will not give the hat to anyone else willingly. Tapping the hat will cause anyone within 10' of the wearer to notice how exceptionally roguish the hat is. Any Acrobatics/Athletics checks made by the wearer have a 10% chance of causing the hat to fall off. Losing the hat means losing 2 CHA (as well as losing the 2 CHA gained by wearing the hat) because the character never look as good again. | J24: Lizardmaaaaan
A25: 43761.791 | B25: Devil's Disk | C25: Concave disk of black glass, 2 feet wide, made from obsidian. Etched with Infernal symbols. | D25: 9000 | E25: Very Rare | F25: 3 lbs | G25: Treasure | H25: When filled with water from the River Styx it becomes a beacon for desperate pleas from mortals. If there is a mortal creature that is in a desperate situation anywhere on the Material Plane the disk can form a connection with that mortal to create a contract. If a contract is made with that creature, it is bound by Asmodeus' will, and the user of the disk may do the following things: § Travel through the Disk to the mortal for up to 10 minutes § Pass objects through the Disk § Reveal a secret to the mortal. You must spend a spell slot to obtain this secret. The higher level the spell slot the more information can be discovered. § Cast a spell through the Disk to a target create that is within 50' of the desperate mortal After a contract is made with a mortal, you can use the disk to contact that mortal again. | J25: Lizardmaaaaan
A26: 43864.997 | B26: Christopher | C26: A metal ring with a line running around the ring that is the wearer's favorite color. This ring gives one the ability to dominate one's does if they are below half of the player's HP. Once they are dominated they serve you as if they are your slave or servant. They will never betray you unless you harm them or someone/something they care about by then which the effects will be lifted and they will become your enemy. Otherwise the duration of the domination last 24 hours and the victim makes a wisdom saving throw with advantage if they broke free from the domination before. (DC is equal to 10 + Intimidation skill) | D26: Priceless | E26: Legendary | F26: N/A | G26: Ring | I26: Requires Attunement
A27: 43979.301 | B27: The Eye of Patch Adams | C27: The Eye of Patch Adams is a small grey pewter orb which can replace a characters missing/removed eye. It allows the user to see the internal workings of all creatures, even if they are wearing armour, you can identify organs, bones and anomalies. | D27: 5000g | E27: Rare | F27: 60g | G27: Wondrous Item | H27: Combat: This eye allows you to pinpoint strike weak-spots and previous injuries. Combat rolls of 19+ count as critical. Passive: You can sense illnesses, cancers, pregnancies and any other medical condition that would have a physical presence in the body. Add one D6 to all healing rolls. | J27: Boba Irid
A28: 44555.757 | B28: Royce | C28: Armor | E28: Rare | G28: Armor

Sheet Working Filter Page
C1: Loot Table Calculator | D1: Filter Value | E1: Filter Rarity | G1: Filter Category
A2: =IF(E2="Mundane", 1, IF(E2="Common", 2, IF(E2="Uncommon", 3, IF(E2="Rare", 4, IF(E2="Very Rare", 5, IF(E2="Legendary", 6, 0)))))) -> 5 | C2: Lowest: | D2: 0 | E2: Very Rare | G2: Wondrous Item
A3: =IF(E3="Mundane", 1, IF(E3="Common", 2, IF(E3="Uncommon", 3, IF(E3="Rare", 4, IF(E3="Very Rare", 5, IF(E3="Legendary", 6, 0)))))) -> 5 | C3: Highest: | D3: 500000 | E3: Very Rare | G3: Armor
A4: D100 Roll | B4: Name | C4: Description | D4: Est. Value | E4: Rarity | F4: Weight | G4: Category | H4: Properties | I4: Requirements | J4: Author | K4: Rarity Number
A5: 42644 | B5: =IFERROR(__xludf.DUMMYFUNCTION("FILTER('Dungeon Loot'!A2:K1004, ('Dungeon Loot'!C2:C1004 > D2), ('Dungeon Loot'!C2:C1004 < D3), ('Dungeon Loot'!J2:J1004 >= A2), ('Dungeon Loot'!J2:J1004 <= A3), ('Dungeon Loot'!F2:F1004=G2) + ('Dungeon Loot'!F2:F1004=G3))"),"Amulet of the Planes") -> Amulet of the Planes | C5: =IFERROR(__xludf.DUMMYFUNCTION("""COMPUTED_VALUE"""),"While wearing this amulet, you can use an action to name a location that you are familiar with on another plane of existence. Then make a DC 15 Intelligence check. On a successful check, you cast the plane shift spell. On a failure , you and each creature"&" and object within 15 feet of you travel to a random destination. Roll a dlOO. On a 1- 60, you travel to a random location on the plane you named. On a 61- 100, you travel to a randomly determined plane of existence. ") -> While wearing this amulet, you can use an action to name a location that you are familiar with on another plane of existence. Then make a DC 15 Intelligence check. On a successful check, you cast the plane shift spell. On a failure , you and each creature and object within 15 feet of you travel to a random destination. Roll a dlOO. On a 1- 60, you travel to a random location on the plane you named. On a 61- 100, you travel to a randomly determined plane of existence. | D5: =IFERROR(__xludf.DUMMYFUNCTION("""COMPUTED_VALUE"""),160000.0) -> 160000 | E5: =IFERROR(__xludf.DUMMYFUNCTION("""COMPUTED_VALUE"""),"Very Rare") -> Very Rare | F5: =IFERROR(__xludf.DUMMYFUNCTION("""COMPUTED_VALUE"""),"n/a") -> n/a | G5: =IFERROR(__xludf.DUMMYFUNCTION("""COMPUTED_VALUE"""),"Wondrous Item") -> Wondrous Item | I5: =IFERROR(__xludf.DUMMYFUNCTION("""COMPUTED_VALUE"""),"Requires Attunement") -> Requires Attunement | J5: =IFERROR(__xludf.DUMMYFUNCTION("""COMPUTED_VALUE"""),"DMG") -> DMG | K5: =IFERROR(__xludf.DUMMYFUNCTION("""COMPUTED_VALUE"""),5.0) -> 5
A6: 11-20 | B6: =IFERROR(__xludf.DUMMYFUNCTION("""COMPUTED_VALUE"""),"Amulets of Inedibility") -> Amulets of Inedibility | C6: =IFERROR(__xludf.DUMMYFUNCTION("""COMPUTED_VALUE"""),"These two amulets are enchanted as a pair and both must be worn at the same time for the enchantment to work. Anything wearing it cannot be considered as food.") -> These two amulets are enchanted as a pair and both must be worn at the same time for the enchantment to work. Anything wearing it cannot be considered as food. | D6: =IFERROR(__xludf.DUMMYFUNCTION("""COMPUTED_VALUE"""),1000.0) -> 1000 | E6: =IFERROR(__xludf.DUMMYFUNCTION("""COMPUTED_VALUE"""),"Very Rare") -> Very Rare | F6: =IFERROR(__xludf.DUMMYFUNCTION("""COMPUTED_VALUE"""),"n/a") -> n/a | G6: =IFERROR(__xludf.DUMMYFUNCTION("""COMPUTED_VALUE"""),"Wondrous Item") -> Wondrous Item | I6: =IFERROR(__xludf.DUMMYFUNCTION("""COMPUTED_VALUE"""),"Requires Attunement") -> Requires Attunement | J6: =IFERROR(__xludf.DUMMYFUNCTION("""COMPUTED_VALUE"""),"PlatypusPal") -> PlatypusPal | K6: =IFERROR(__xludf.DUMMYFUNCTION("""COMPUTED_VALUE"""),5.0) -> 5
A7: 21 - 30 | B7: =IFERROR(__xludf.DUMMYFUNCTION("""COMPUTED_VALUE"""),"Anderson's Medallion") -> Anderson's Medallion | C7: =IFERROR(__xludf.DUMMYFUNCTION("""COMPUTED_VALUE"""),"Once per day, you can remove AC of target granted by armor, last until end of your next turn. User takes -2 to AC for same duration. (I think lasting until the end of combat might be a bit op, also I have named it after Hans Christian Anderson because it"&" makes me thing of the Emperor's New Clothes)") -> Once per day, you can remove AC of target granted by armor, last until end of your next turn. User takes -2 to AC for same duration. (I think lasting until the end of combat might be a bit op, also I have named it after Hans Christian Anderson because it makes me thing of the Emperor's New Clothes) | D7: =IFERROR(__xludf.DUMMYFUNCTION("""COMPUTED_VALUE"""),400.0) -> 400 | E7: =IFERROR(__xludf.DUMMYFUNCTION("""COMPUTED_VALUE"""),"Very Rare") -> Very Rare | F7: =IFERROR(__xludf.DUMMYFUNCTION("""COMPUTED_VALUE"""),1.0) -> 1 | G7: =IFERROR(__xludf.DUMMYFUNCTION("""COMPUTED_VALUE"""),"Wondrous Item") -> Wondrous Item | J7: =IFERROR(__xludf.DUMMYFUNCTION("""COMPUTED_VALUE"""),"PlatypusPal") -> PlatypusPal | K7: =IFERROR(__xludf.DUMMYFUNCTION("""COMPUTED_VALUE"""),5.0) -> 5
A8: 31 - 40 | B8: =IFERROR(__xludf.DUMMYFUNCTION("""COMPUTED_VALUE"""),"Animated Shield") -> Animated Shield | C8: =IFERROR(__xludf.DUMMYFUNCTION("""COMPUTED_VALUE"""),"While holding this shield, you can speak its command word as a bonus action to cause it to animate. The shield leaps into the air and hovers in your space to protect you as if you were wielding it, leaving your hands free. The shield remains animated for "&"1 minute, until you use a bonus action to end this effect, or until you are incapacitated or die, at which point the shield falls to the ground or into your hand if you have one free.") -> While holding this shield, you can speak its command word as a bonus action to cause it to animate. The shield leaps into the air and hovers in your space to protect you as if you were wielding it, leaving your hands free. The shield remains animated for 1 minute, until you use a bonus action to end this effect, or until you are incapacitated or die, at which point the shield falls to the ground or into your hand if you have one free. | D8: =IFERROR(__xludf.DUMMYFUNCTION("""COMPUTED_VALUE"""),6000.0) -> 6000 | E8: =IFERROR(__xludf.DUMMYFUNCTION("""COMPUTED_VALUE"""),"Very Rare") -> Very Rare | F8: =IFERROR(__xludf.DUMMYFUNCTION("""COMPUTED_VALUE"""),6.0) -> 6 | G8: =IFERROR(__xludf.DUMMYFUNCTION("""COMPUTED_VALUE"""),"Armor") -> Armor | I8: =IFERROR(__xludf.DUMMYFUNCTION("""COMPUTED_VALUE"""),"Requires Attunement") -> Requires Attunement | J8: =IFERROR(__xludf.DUMMYFUNCTION("""COMPUTED_VALUE"""),"DMG") -> DMG | K8: =IFERROR(__xludf.DUMMYFUNCTION("""COMPUTED_VALUE"""),5.0) -> 5
A9: 41 - 50 | B9: =IFERROR(__xludf.DUMMYFUNCTION("""COMPUTED_VALUE"""),"Armor +2") -> Armor +2 | C9: =IFERROR(__xludf.DUMMYFUNCTION("""COMPUTED_VALUE"""),"You have a +2 bonus to AC while wearing this armor.") -> You have a +2 bonus to AC while wearing this armor. | D9: =IFERROR(__xludf.DUMMYFUNCTION("""COMPUTED_VALUE"""),6000.0) -> 6000 | E9: =IFERROR(__xludf.DUMMYFUNCTION("""COMPUTED_VALUE"""),"Very Rare") -> Very Rare | F9: =IFERROR(__xludf.DUMMYFUNCTION("""COMPUTED_VALUE"""),"8 - 60") -> 8 - 60 | G9: =IFERROR(__xludf.DUMMYFUNCTION("""COMPUTED_VALUE"""),"Armor") -> Armor | H9: =IFERROR(__xludf.DUMMYFUNCTION("""COMPUTED_VALUE"""),"Light, Medium or Heavy") -> Light, Medium or Heavy | J9: =IFERROR(__xludf.DUMMYFUNCTION("""COMPUTED_VALUE"""),"DMG") -> DMG | K9: =IFERROR(__xludf.DUMMYFUNCTION("""COMPUTED_VALUE"""),5.0) -> 5
A10: 51 - 55 | B10: =IFERROR(__xludf.DUMMYFUNCTION("""COMPUTED_VALUE"""),"Bag of Devouring") -> Bag of Devouring | C10: =IFERROR(__xludf.DUMMYFUNCTION("""COMPUTED_VALUE"""),"This bag superficially resembles a bag of holding but is a feeding orifice for a gigantic extradimensional creature. Turning the bag inside out closes the orifice. The extradimensional creature attached to the bag can sense whatever is placed inside the b"&"ag. Animal or vegetable matter placed wholly in the bag is devoured and lost forever. When part of a living creature is placed in the bag, as happens when someone reaches inside it, there is a 50 percent chance that the creature is pulled inside the bag. "&"A creature inside the bag can use its action to try to escape with a successful DC 15 Strength check. Another creature can use its action to reach into the bag to pull a creature out, doing so with a successful DC 20 Strength check (provided it isn't pull"&"ed inside the bag first). Any creature that starts its turn inside the bag is devoured, its body destroyed. Inanimate objects can be stored in the bag, which can hold a cubic foot of such material. However, once each day, the bag swallows any objects insi"&"de it and spits them out into another plane of existence. The DM determines the time and plane. If the bag is pierced or torn, it is destroyed, and anything contained within it is transported to a random location on the Astral Plane. ") -> This bag superficially resembles a bag of holding but is a feeding orifice for a gigantic extradimensional creature. Turning the bag inside out closes the orifice. The extradimensional creature attached to the bag can sense whatever is placed inside the bag. Animal or vegetable matter placed wholly in the bag is devoured and lost forever. When part of a living creature is placed in the bag, as happens when someone reaches inside it, there is a 50 percent chance that the creature is pulled inside the bag. A creature inside the bag can use its action to try to escape with a successful DC 15 Strength check. Another creature can use its action to reach into the bag to pull a creature out, doing so with a successful DC 20 Strength check (provided it isn't pulled inside the bag first). Any creature that starts its turn inside the bag is devoured, its body destroyed. Inanimate objects can be stored in the bag, which can hold a cubic foot of such material. However, once each day, the bag swallows any objects inside it and spits them out into another plane of existence. The DM determines the time and plane. If the bag is pierced or torn, it is destroyed, and anything contained within it is transported to a random location on the Astral Plane. | D10: =IFERROR(__xludf.DUMMYFUNCTION("""COMPUTED_VALUE"""),10000.0) -> 10000 | E10: =IFERROR(__xludf.DUMMYFUNCTION("""COMPUTED_VALUE"""),"Very Rare") -> Very Rare | F10: =IFERROR(__xludf.DUMMYFUNCTION("""COMPUTED_VALUE"""),15.0) -> 15 | G10: =IFERROR(__xludf.DUMMYFUNCTION("""COMPUTED_VALUE"""),"Wondrous Item") -> Wondrous Item | J10: =IFERROR(__xludf.DUMMYFUNCTION("""COMPUTED_VALUE"""),"DMG") -> DMG | K10: =IFERROR(__xludf.DUMMYFUNCTION("""COMPUTED_VALUE"""),5.0) -> 5
A11: 56 - 60 | B11: =IFERROR(__xludf.DUMMYFUNCTION("""COMPUTED_VALUE"""),"Bardweave Parisol") -> Bardweave Parisol | C11: =IFERROR(__xludf.DUMMYFUNCTION("""COMPUTED_VALUE"""),"A beautiful, vibrantly colorful cloth parasol with a light wooden handle. The object feels delicate and weightless.") -> A beautiful, vibrantly colorful cloth parasol with a light wooden handle. The object feels delicate and weightless. | D11: =IFERROR(__xludf.DUMMYFUNCTION("""COMPUTED_VALUE"""),1500.0) -> 1500 | E11: =IFERROR(__xludf.DUMMYFUNCTION("""COMPUTED_VALUE"""),"Very Rare") -> Very Rare | G11: =IFERROR(__xludf.DUMMYFUNCTION("""COMPUTED_VALUE"""),"Wondrous Item") -> Wondrous Item | H11: =IFERROR(__xludf.DUMMYFUNCTION("""COMPUTED_VALUE"""),"As a reaction, you may open this parasol to defend you, provided it is easily reachable on your character. When you make a dexterity save, you may use your reaction to open the magical parasol, giving you resistance to all damage. If you suffer more than "&"10 damage after this resistance, the parasol is damaged and can no longer protect you. It can be repaired with a sewing kit or a proficient tailor.") -> As a reaction, you may open this parasol to defend you, provided it is easily reachable on your character. When you make a dexterity save, you may use your reaction to open the magical parasol, giving you resistance to all damage. If you suffer more than 10 damage after this resistance, the parasol is damaged and can no longer protect you. It can be repaired with a sewing kit or a proficient tailor. | J11: =IFERROR(__xludf.DUMMYFUNCTION("""COMPUTED_VALUE"""),"/u/gimme_some_sunshine") -> /u/gimme_some_sunshine | K11: =IFERROR(__xludf.DUMMYFUNCTION("""COMPUTED_VALUE"""),5.0) -> 5
A12: 61 - 65 | B12: =IFERROR(__xludf.DUMMYFUNCTION("""COMPUTED_VALUE"""),"Belt of Fire Giant Strength") -> Belt of Fire Giant Strength | C12: =IFERROR(__xludf.DUMMYFUNCTION("""COMPUTED_VALUE"""),"While wearing this belt, your Strength score changes to 25. If your Strength is already equal to or greater than 25, the item has no effect on you.") -> While wearing this belt, your Strength score changes to 25. If your Strength is already equal to or greater than 25, the item has no effect on you. | D12: =IFERROR(__xludf.DUMMYFUNCTION("""COMPUTED_VALUE"""),24000.0) -> 24000 | E12: =IFERROR(__xludf.DUMMYFUNCTION("""COMPUTED_VALUE"""),"Very Rare") -> Very Rare | F12: =IFERROR(__xludf.DUMMYFUNCTION("""COMPUTED_VALUE"""),1.0) -> 1 | G12: =IFERROR(__xludf.DUMMYFUNCTION("""COMPUTED_VALUE"""),"Wondrous Item") -> Wondrous Item | I12: =IFERROR(__xludf.DUMMYFUNCTION("""COMPUTED_VALUE"""),"Requires Attunement") -> Requires Attunement | J12: =IFERROR(__xludf.DUMMYFUNCTION("""COMPUTED_VALUE"""),"DMG") -> DMG | K12: =IFERROR(__xludf.DUMMYFUNCTION("""COMPUTED_VALUE"""),5.0) -> 5
A13: 66 - 70 | B13: =IFERROR(__xludf.DUMMYFUNCTION("""COMPUTED_VALUE"""),"Belt of Frost Giant Strength") -> Belt of Frost Giant Strength | C13: =IFERROR(__xludf.DUMMYFUNCTION("""COMPUTED_VALUE"""),"While wearing this belt, your Strength score changes to 23. If your Strength is already equal to or greater than 23, the item has no effect on you.") -> While wearing this belt, your Strength score changes to 23. If your Strength is already equal to or greater than 23, the item has no effect on you. | D13: =IFERROR(__xludf.DUMMYFUNCTION("""COMPUTED_VALUE"""),19000.0) -> 19000 | E13: =IFERROR(__xludf.DUMMYFUNCTION("""COMPUTED_VALUE"""),"Very Rare") -> Very Rare | F13: =IFERROR(__xludf.DUMMYFUNCTION("""COMPUTED_VALUE"""),1.0) -> 1 | G13: =IFERROR(__xludf.DUMMYFUNCTION("""COMPUTED_VALUE"""),"Wondrous Item") -> Wondrous Item | I13: =IFERROR(__xludf.DUMMYFUNCTION("""COMPUTED_VALUE"""),"Requires Attunement") -> Requires Attunement | J13: =IFERROR(__xludf.DUMMYFUNCTION("""COMPUTED_VALUE"""),"DMG") -> DMG | K13: =IFERROR(__xludf.DUMMYFUNCTION("""COMPUTED_VALUE"""),5.0) -> 5
A14: 71 - 75 | B14: =IFERROR(__xludf.DUMMYFUNCTION("""COMPUTED_VALUE"""),"Belt of Stone Giant Strength") -> Belt of Stone Giant Strength | C14: =IFERROR(__xludf.DUMMYFUNCTION("""COMPUTED_VALUE"""),"While wearing this belt, your Strength score changes to 23. If your Strength is already equal to or greater than 23, the item has no effect on you.") -> While wearing this belt, your Strength score changes to 23. If your Strength is already equal to or greater than 23, the item has no effect on you. | D14: =IFERROR(__xludf.DUMMYFUNCTION("""COMPUTED_VALUE"""),19000.0) -> 19000 | E14: =IFERROR(__xludf.DUMMYFUNCTION("""COMPUTED_VALUE"""),"Very Rare") -> Very Rare | F14: =IFERROR(__xludf.DUMMYFUNCTION("""COMPUTED_VALUE"""),1.0) -> 1 | G14: =IFERROR(__xludf.DUMMYFUNCTION("""COMPUTED_VALUE"""),"Wondrous Item") -> Wondrous Item | I14: =IFERROR(__xludf.DUMMYFUNCTION("""COMPUTED_VALUE"""),"Requires Attunement") -> Requires Attunement | J14: =IFERROR(__xludf.DUMMYFUNCTION("""COMPUTED_VALUE"""),"DMG") -> DMG | K14: =IFERROR(__xludf.DUMMYFUNCTION("""COMPUTED_VALUE"""),5.0) -> 5
A15: 76 - 80 | B15: =IFERROR(__xludf.DUMMYFUNCTION("""COMPUTED_VALUE"""),"Black Obelisk") -> Black Obelisk | C15: =IFERROR(__xludf.DUMMYFUNCTION("""COMPUTED_VALUE"""),"A plain, unadorned black obelisk. If brought above ground and into the open, the obelisk will draw down a near-constant barrage of lightning to itself – even if the sky is clear.") -> A plain, unadorned black obelisk. If brought above ground and into the open, the obelisk will draw down a near-constant barrage of lightning to itself – even if the sky is clear. | D15: =IFERROR(__xludf.DUMMYFUNCTION("""COMPUTED_VALUE"""),17500.0) -> 17500 | E15: =IFERROR(__xludf.DUMMYFUNCTION("""COMPUTED_VALUE"""),"Very Rare") -> Very Rare | F15: =IFERROR(__xludf.DUMMYFUNCTION("""COMPUTED_VALUE"""),1000.0) -> 1000 | G15: =IFERROR(__xludf.DUMMYFUNCTION("""COMPUTED_VALUE"""),"Wondrous Item") -> Wondrous Item | J15: =IFERROR(__xludf.DUMMYFUNCTION("""COMPUTED_VALUE"""),"PlatypusPal") -> PlatypusPal | K15: =IFERROR(__xludf.DUMMYFUNCTION("""COMPUTED_VALUE"""),5.0) -> 5
A16: 81 - 85 | B16: =IFERROR(__xludf.DUMMYFUNCTION("""COMPUTED_VALUE"""),"Bloodied Harp") -> Bloodied Harp | C16: =IFERROR(__xludf.DUMMYFUNCTION("""COMPUTED_VALUE"""),"An old looking brass harp that has only 3 strings left. The strings are flecked with rust, or so it seems. Holding it gives you a feeling of cold anxiety.") -> An old looking brass harp that has only 3 strings left. The strings are flecked with rust, or so it seems. Holding it gives you a feeling of cold anxiety. | D16: =IFERROR(__xludf.DUMMYFUNCTION("""COMPUTED_VALUE"""),2500.0) -> 2500 | E16: =IFERROR(__xludf.DUMMYFUNCTION("""COMPUTED_VALUE"""),"Very Rare") -> Very Rare | G16: =IFERROR(__xludf.DUMMYFUNCTION("""COMPUTED_VALUE"""),"Wondrous Item") -> Wondrous Item | H16: =IFERROR(__xludf.DUMMYFUNCTION("""COMPUTED_VALUE"""),"Plucking the harp strings causes you great pain and triggers magical effects. The first string deals 1d6 damage to you, and casts the ""sleep"" spell at first level, using Charisma. The second string deals 2d6 damage to you, and 2d6 damage to all targets "&"within 20 feet. The third string deals 3d6 damage to you, and heals a target in 20 feet for 4d6. You may pluck 3 strings each day.") -> Plucking the harp strings causes you great pain and triggers magical effects. The first string deals 1d6 damage to you, and casts the "sleep" spell at first level, using Charisma. The second string deals 2d6 damage to you, and 2d6 damage to all targets within 20 feet. The third string deals 3d6 damage to you, and heals a target in 20 feet for 4d6. You may pluck 3 strings each day. | J16: =IFERROR(__xludf.DUMMYFUNCTION("""COMPUTED_VALUE"""),"/u/gimme_some_sunshine") -> /u/gimme_some_sunshine | K16: =IFERROR(__xludf.DUMMYFUNCTION("""COMPUTED_VALUE"""),5.0) -> 5
A17: 86 - 90 | B17: =IFERROR(__xludf.DUMMYFUNCTION("""COMPUTED_VALUE"""),"Brazier of Infinite Imps") -> Brazier of Infinite Imps | C17: =IFERROR(__xludf.DUMMYFUNCTION("""COMPUTED_VALUE"""),"Brazier of infinite imps. 1d4 imps spawn every 24 hours. If they are not killed by the time the brazier spawns a new set, the previous imps die and vanish.") -> Brazier of infinite imps. 1d4 imps spawn every 24 hours. If they are not killed by the time the brazier spawns a new set, the previous imps die and vanish. | D17: =IFERROR(__xludf.DUMMYFUNCTION("""COMPUTED_VALUE"""),500.0) -> 500 | E17: =IFERROR(__xludf.DUMMYFUNCTION("""COMPUTED_VALUE"""),"Very Rare") -> Very Rare | F17: =IFERROR(__xludf.DUMMYFUNCTION("""COMPUTED_VALUE"""),2.0) -> 2 | G17: =IFERROR(__xludf.DUMMYFUNCTION("""COMPUTED_VALUE"""),"Wondrous Item") -> Wondrous Item | K17: =IFERROR(__xludf.DUMMYFUNCTION("""COMPUTED_VALUE"""),5.0) -> 5
A18: 91 | B18: =IFERROR(__xludf.DUMMYFUNCTION("""COMPUTED_VALUE"""),"Buzzing Buckler") -> Buzzing Buckler | C18: =IFERROR(__xludf.DUMMYFUNCTION("""COMPUTED_VALUE"""),"A wooden buckler with a burned-in sigil of a bee on the shield face. It vibrates ferociously when struck.") -> A wooden buckler with a burned-in sigil of a bee on the shield face. It vibrates ferociously when struck. | D18: =IFERROR(__xludf.DUMMYFUNCTION("""COMPUTED_VALUE"""),2500.0) -> 2500 | E18: =IFERROR(__xludf.DUMMYFUNCTION("""COMPUTED_VALUE"""),"Very Rare") -> Very Rare | G18: =IFERROR(__xludf.DUMMYFUNCTION("""COMPUTED_VALUE"""),"Armor") -> Armor | H18: =IFERROR(__xludf.DUMMYFUNCTION("""COMPUTED_VALUE"""),"Adds no armor. If you are the victim of a ranged attacked, you may use your reaction to increase your AC by +1. If you choose to do this, and the attack fails to hit you, the projectile is deflected by your shield, and bursts into a cloud of angry bees th"&"at will seek the attacker and sting it relentlessly, causing 1d6 poison damage at the beginning of each of their turns for one minute, or until you recall the bees. The victim also suffers disadvantage on attack rolls and can no longer maintain concentrat"&"ion.") -> Adds no armor. If you are the victim of a ranged attacked, you may use your reaction to increase your AC by +1. If you choose to do this, and the attack fails to hit you, the projectile is deflected by your shield, and bursts into a cloud of angry bees that will seek the attacker and sting it relentlessly, causing 1d6 poison damage at the beginning of each of their turns for one minute, or until you recall the bees. The victim also suffers disadvantage on attack rolls and can no longer maintain concentration. | J18: =IFERROR(__xludf.DUMMYFUNCTION("""COMPUTED_VALUE"""),"/u/gimme_some_sunshine") -> /u/gimme_some_sunshine | K18: =IFERROR(__xludf.DUMMYFUNCTION("""COMPUTED_VALUE"""),5.0) -> 5
A19: 92 | B19: =IFERROR(__xludf.DUMMYFUNCTION("""COMPUTED_VALUE"""),"Candle of Invocation") -> Candle of Invocation | C19: =IFERROR(__xludf.DUMMYFUNCTION("""COMPUTED_VALUE"""),"This slender taper is dedicated to a deity and shares that deity's alignment. The candle's alignment can be detected with the detect evil and good spell. The DM chooses the god and associated alignment or determines the alignment randomly. The candle's ma"&"gic is activated when the candle is lit, which requires an action. After burning for 4 hours, the candle is destroyed. You can snuff it out early for use at a later time. Deduct the time it burned in increments of 1 minute from the candle's total burn tim"&"e. While lit, the candle sheds dim light in a 30-foot radius. Any creature within that light whose alignment matches that of the candle makes attack rolls, saving throws, and ability checks with advantage. In addition, a cleric or druid in the light whose"&" alignment matches the candle's can cast 1st-level spells he or she has prepared without expending spell slots, though the spell's effect is as if cast with a 1st-level slot. Alternatively, when you light the candle for the first time, you can cast the ga"&"te spell with it. Doing so destroys the candle.") -> This slender taper is dedicated to a deity and shares that deity's alignment. The candle's alignment can be detected with the detect evil and good spell. The DM chooses the god and associated alignment or determines the alignment randomly. The candle's magic is activated when the candle is lit, which requires an action. After burning for 4 hours, the candle is destroyed. You can snuff it out early for use at a later time. Deduct the time it burned in increments of 1 minute from the candle's total burn time. While lit, the candle sheds dim light in a 30-foot radius. Any creature within that light whose alignment matches that of the candle makes attack rolls, saving throws, and ability checks with advantage. In addition, a cleric or druid in the light whose alignment matches the candle's can cast 1st-level spells he or she has prepared without expending spell slots, though the spell's effect is as if cast with a 1st-level slot. Alternatively, when you light the candle for the first time, you can cast the gate spell with it. Doing so destroys the candle. | D19: =IFERROR(__xludf.DUMMYFUNCTION("""COMPUTED_VALUE"""),8400.0) -> 8400 | E19: =IFERROR(__xludf.DUMMYFUNCTION("""COMPUTED_VALUE"""),"Very Rare") -> Very Rare | F19: =IFERROR(__xludf.DUMMYFUNCTION("""COMPUTED_VALUE"""),0.5) -> 0.5 | G19: =IFERROR(__xludf.DUMMYFUNCTION("""COMPUTED_VALUE"""),"Wondrous Item") -> Wondrous Item | I19: =IFERROR(__xludf.DUMMYFUNCTION("""COMPUTED_VALUE"""),"Requires Attunement") -> Requires Attunement | J19: =IFERROR(__xludf.DUMMYFUNCTION("""COMPUTED_VALUE"""),"DMG") -> DMG | K19: =IFERROR(__xludf.DUMMYFUNCTION("""COMPUTED_VALUE"""),5.0) -> 5
A20: 93 | B20: =IFERROR(__xludf.DUMMYFUNCTION("""COMPUTED_VALUE"""),"Earthbreaker Totem") -> Earthbreaker Totem | C20: =IFERROR(__xludf.DUMMYFUNCTION("""COMPUTED_VALUE"""),"A thick shaft of wood with totemic carvings. It has a slight gradual spike shape, being thinner and sharper at one end, and thick and flat at the other.") -> A thick shaft of wood with totemic carvings. It has a slight gradual spike shape, being thinner and sharper at one end, and thick and flat at the other. | D20: =IFERROR(__xludf.DUMMYFUNCTION("""COMPUTED_VALUE"""),1500.0) -> 1500 | E20: =IFERROR(__xludf.DUMMYFUNCTION("""COMPUTED_VALUE"""),"Very Rare") -> Very Rare | G20: =IFERROR(__xludf.DUMMYFUNCTION("""COMPUTED_VALUE"""),"Wondrous Item") -> Wondrous Item | H20: =IFERROR(__xludf.DUMMYFUNCTION("""COMPUTED_VALUE"""),"You may use your action to plant this into any reasonably soft ground. If the totem takes 15 bludgeoning damage (from being forcibly smashed deeper into the ground), it will trigger an earthquake, causing 4d12 thunder damage to all ground-bound targets wi"&"thin 200 feet. Constructs and buildings are considered vulnerable. Targets within 10 feet of the totem are unaffected.") -> You may use your action to plant this into any reasonably soft ground. If the totem takes 15 bludgeoning damage (from being forcibly smashed deeper into the ground), it will trigger an earthquake, causing 4d12 thunder damage to all ground-bound targets within 200 feet. Constructs and buildings are considered vulnerable. Targets within 10 feet of the totem are unaffected. | J20: =IFERROR(__xludf.DUMMYFUNCTION("""COMPUTED_VALUE"""),"/u/gimme_some_sunshine") -> /u/gimme_some_sunshine | K20: =IFERROR(__xludf.DUMMYFUNCTION("""COMPUTED_VALUE"""),5.0) -> 5
A21: 94 | B21: =IFERROR(__xludf.DUMMYFUNCTION("""COMPUTED_VALUE"""),"Encyclopedia Approximatus") -> Encyclopedia Approximatus | C21: =IFERROR(__xludf.DUMMYFUNCTION("""COMPUTED_VALUE"""),"A large, unmarked blue tome. Every page inside is blank.") -> A large, unmarked blue tome. Every page inside is blank. | D21: =IFERROR(__xludf.DUMMYFUNCTION("""COMPUTED_VALUE"""),500.0) -> 500 | E21: =IFERROR(__xludf.DUMMYFUNCTION("""COMPUTED_VALUE"""),"Very Rare") -> Very Rare | G21: =IFERROR(__xludf.DUMMYFUNCTION("""COMPUTED_VALUE"""),"Wondrous Item") -> Wondrous Item | H21: =IFERROR(__xludf.DUMMYFUNCTION("""COMPUTED_VALUE"""),"Speak any subject to its spine and roll 1d4. On a 4, the reader is given a couple pages of accurate and detailed information on the subject (more accurate and detailed the most specific you are). All other rolls provides the user with approximate informat"&"ion, with regular errors. Regardless of accuracy, it's always written in a condescending tone.") -> Speak any subject to its spine and roll 1d4. On a 4, the reader is given a couple pages of accurate and detailed information on the subject (more accurate and detailed the most specific you are). All other rolls provides the user with approximate information, with regular errors. Regardless of accuracy, it's always written in a condescending tone. | J21: =IFERROR(__xludf.DUMMYFUNCTION("""COMPUTED_VALUE"""),"/u/BardicFire") -> /u/BardicFire | K21: =IFERROR(__xludf.DUMMYFUNCTION("""COMPUTED_VALUE"""),5.0) -> 5
A22: 95 | B22: =IFERROR(__xludf.DUMMYFUNCTION("""COMPUTED_VALUE"""),"Harkol's Agonizing Instruments") -> Harkol's Agonizing Instruments | C22: =IFERROR(__xludf.DUMMYFUNCTION("""COMPUTED_VALUE"""),"A cloth tool-roll that contains six needles of varying thickness. A melody is embroidered on the inside of the roll.") -> A cloth tool-roll that contains six needles of varying thickness. A melody is embroidered on the inside of the roll. | D22: =IFERROR(__xludf.DUMMYFUNCTION("""COMPUTED_VALUE"""),500.0) -> 500 | E22: =IFERROR(__xludf.DUMMYFUNCTION("""COMPUTED_VALUE"""),"Very Rare") -> Very Rare | G22: =IFERROR(__xludf.DUMMYFUNCTION("""COMPUTED_VALUE"""),"Wondrous Item") -> Wondrous Item | H22: =IFERROR(__xludf.DUMMYFUNCTION("""COMPUTED_VALUE"""),"While humming the melody inscribed in the roll, the needles will move very slowly and very accurately according to the user's will. It would not be possible to cause bodily harm to an unrestrained creature by using these.") -> While humming the melody inscribed in the roll, the needles will move very slowly and very accurately according to the user's will. It would not be possible to cause bodily harm to an unrestrained creature by using these. | J22: =IFERROR(__xludf.DUMMYFUNCTION("""COMPUTED_VALUE"""),"/u/gimme_some_sunshine") -> /u/gimme_some_sunshine | K22: =IFERROR(__xludf.DUMMYFUNCTION("""COMPUTED_VALUE"""),5.0) -> 5
A23: 96 | B23: =IFERROR(__xludf.DUMMYFUNCTION("""COMPUTED_VALUE"""),"Links of Truth") -> Links of Truth | C23: =IFERROR(__xludf.DUMMYFUNCTION("""COMPUTED_VALUE"""),"Plain, but exceptionally clean chainmail that feels light, and always cold.") -> Plain, but exceptionally clean chainmail that feels light, and always cold. | D23: =IFERROR(__xludf.DUMMYFUNCTION("""COMPUTED_VALUE"""),1250.0) -> 1250 | E23: =IFERROR(__xludf.DUMMYFUNCTION("""COMPUTED_VALUE"""),"Very Rare") -> Very Rare | G23: =IFERROR(__xludf.DUMMYFUNCTION("""COMPUTED_VALUE"""),"Armor") -> Armor | H23: =IFERROR(__xludf.DUMMYFUNCTION("""COMPUTED_VALUE"""),"Grants 13 AC +Dex. If the bearer tells a lie, the armor will fall into hundreds of metal rings. If the lie is redeemed, the armor will reassemble itself.") -> Grants 13 AC +Dex. If the bearer tells a lie, the armor will fall into hundreds of metal rings. If the lie is redeemed, the armor will reassemble itself. | J23: =IFERROR(__xludf.DUMMYFUNCTION("""COMPUTED_VALUE"""),"/u/gimme_some_sunshine") -> /u/gimme_some_sunshine | K23: =IFERROR(__xludf.DUMMYFUNCTION("""COMPUTED_VALUE"""),5.0) -> 5
A24: 97 | B24: =IFERROR(__xludf.DUMMYFUNCTION("""COMPUTED_VALUE"""),"Mother's Love") -> Mother's Love | C24: =IFERROR(__xludf.DUMMYFUNCTION("""COMPUTED_VALUE"""),"A gold-rimmed cobalt locket inscribed with draconic runes. Inside is a small replaceable portrait.") -> A gold-rimmed cobalt locket inscribed with draconic runes. Inside is a small replaceable portrait. | D24: =IFERROR(__xludf.DUMMYFUNCTION("""COMPUTED_VALUE"""),1250.0) -> 1250 | E24: =IFERROR(__xludf.DUMMYFUNCTION("""COMPUTED_VALUE"""),"Very Rare") -> Very Rare | G24: =IFERROR(__xludf.DUMMYFUNCTION("""COMPUTED_VALUE"""),"Wondrous Item") -> Wondrous Item | H24: =IFERROR(__xludf.DUMMYFUNCTION("""COMPUTED_VALUE"""),"Requires attunement by someone of female sex. While wearing this magical item, the wearer gains the following benefits: Whenever the wearer has to make a death saving throw, they can roll a 1d4 and add the rolled number to the total. This bonus is 1d4+2 "&"if the wearer is pregnant. The wearer can choose to turn a death saving throw roll into a critical success, but the locket's magic then fades for one full year. The locket can be restored if specifically targeted by a Greater Restoration spell after one "&"month. The wearer has advantage on Charisma-based skill checks and saving throws against individuals of early childhood.") -> Requires attunement by someone of female sex. While wearing this magical item, the wearer gains the following benefits: Whenever the wearer has to make a death saving throw, they can roll a 1d4 and add the rolled number to the total. This bonus is 1d4+2 if the wearer is pregnant. The wearer can choose to turn a death saving throw roll into a critical success, but the locket's magic then fades for one full year. The locket can be restored if specifically targeted by a Greater Restoration spell after one month. The wearer has advantage on Charisma-based skill checks and saving throws against individuals of early childhood. | J24: =IFERROR(__xludf.DUMMYFUNCTION("""COMPUTED_VALUE"""),"/u/BrainBlowX") -> /u/BrainBlowX | K24: =IFERROR(__xludf.DUMMYFUNCTION("""COMPUTED_VALUE"""),5.0) -> 5
A25: 98 | B25: =IFERROR(__xludf.DUMMYFUNCTION("""COMPUTED_VALUE"""),"Necklace of the Fang Pact") -> Necklace of the Fang Pact | C25: =IFERROR(__xludf.DUMMYFUNCTION("""COMPUTED_VALUE"""),"This fiber necklace contains beads that separate several teeth from a variety of creatures. All together, it can support up to 7 teeth. ") -> This fiber necklace contains beads that separate several teeth from a variety of creatures. All together, it can support up to 7 teeth. | D25: =IFERROR(__xludf.DUMMYFUNCTION("""COMPUTED_VALUE"""),5000.0) -> 5000 | E25: =IFERROR(__xludf.DUMMYFUNCTION("""COMPUTED_VALUE"""),"Very Rare") -> Very Rare | G25: =IFERROR(__xludf.DUMMYFUNCTION("""COMPUTED_VALUE"""),"Wondrous Item") -> Wondrous Item | H25: =IFERROR(__xludf.DUMMYFUNCTION("""COMPUTED_VALUE"""),"While wearing this amulet, you can use an action to sap the remaining essence from a creature that has been brought to 0 hit points. Doing so turns the creature's flesh into ash and forges its life force into a tooth appropriate for its type which magical"&"ly binds itself to the amulet. Each tooth has a type and a property. As a ritual, you can expend one tooth to gain its property for 24 hours or until a new ritual has been performed. Constructs, Oozes, and Plants are unaffected by this item. Undead whose"&" essence you sap grant you a tooth with the type that it possessed in life rather than undeath. *Aberrations: You can magically transmit simple messages and images to any creature within 120 ft. that can understand a Language. This form of telepathy does"&"n't allow the receiving creature to telepathically respond. *Beasts: Your hit point maximum increases by an amount equal to twice your level. *Celestials: As an action, you can touch a target and remove any curse, disease, poison, blindness, or deafness"&" condition. *Dragons: Your breath weapon gains a recharge of 6 and its damage die is increased to d8. *Elemental: You choose acid, cold, fire, lightning, poison, or thunder and gain resistance to that element. *Fey: Touching a creature, you magically k"&"now the creature's current emotional state. If the target fails a Charisma saving throw, you also know the creature's alignment. Celestials, Fiends, and Undead automatically fail the saving throw. *Fiends: You gain advantage on saving throws against Spel"&"ls and other magical effects. *Giants: Your Strength score is 21. This property has no effect on you if your Strength is already 21 or higher without this necklace. *Humanoids: You become proficient in any two skills. Your proficiency bonus is doubled f"&"or any ability check you make that uses either of the chosen proficiencies. *Monstrosities: You gain Darkvision 60 Ft. and Tremorsense 60 Ft. In addition, you gain a keen sense of hearing and smelling which grants you advantage on Wisdom (Perception) che"&"cks that rely on hearing or smell.") -> While wearing this amulet, you can use an action to sap the remaining essence from a creature that has been brought to 0 hit points. Doing so turns the creature's flesh into ash and forges its life force into a tooth appropriate for its type which magically binds itself to the amulet. Each tooth has a type and a property. As a ritual, you can expend one tooth to gain its property for 24 hours or until a new ritual has been performed. Constructs, Oozes, and Plants are unaffected by this item. Undead whose essence you sap grant you a tooth with the type that it possessed in life rather than undeath. *Aberrations: You can magically transmit simple messages and images to any creature within 120 ft. that can understand a Language. This form of telepathy doesn't allow the receiving creature to telepathically respond. *Beasts: Your hit point maximum increases by an amount equal to twice your level. *Celestials: As an action, you can touch a target and remove any curse, disease, poison, blindness, or deafness condition. *Dragons: Your breath weapon gains a recharge of 6 and its damage die is increased to d8. *Elemental: You choose acid, cold, fire, lightning, poison, or thunder and gain resistance to that element. *Fey: Touching a creature, you magically know the creature's current emotional state. If the target fails a Charisma saving throw, you also know the creature's alignment. Celestials, Fiends, and Undead automatically fail the saving throw. *Fiends: You gain advantage on saving throws against Spells and other magical effects. *Giants: Your Strength score is 21. This property has no effect on you if your Strength is already 21 or higher without this necklace. *Humanoids: You become proficient in any two skills. Your proficiency bonus is doubled for any ability check you make that uses either of the chosen proficiencies. *Monstrosities: You gain Darkvision 60 Ft. and Tremorsense 60 Ft. In addition, you gain a keen sense of hearing and smelling which grants you advantage on Wisdom (Perception) checks that rely on hearing or smell. | I25: =IFERROR(__xludf.DUMMYFUNCTION("""COMPUTED_VALUE"""),"Requires Attunement") -> Requires Attunement | J25: =IFERROR(__xludf.DUMMYFUNCTION("""COMPUTED_VALUE"""),"Fin Fen") -> Fin Fen | K25: =IFERROR(__xludf.DUMMYFUNCTION("""COMPUTED_VALUE"""),5.0) -> 5
A26: 99 | B26: =IFERROR(__xludf.DUMMYFUNCTION("""COMPUTED_VALUE"""),"Stick of Rage") -> Stick of Rage | C26: =IFERROR(__xludf.DUMMYFUNCTION("""COMPUTED_VALUE"""),"A carved, thumb-width stick of great sturdiness. Holding it fills you with a furious urge to break it.") -> A carved, thumb-width stick of great sturdiness. Holding it fills you with a furious urge to break it. | D26: =IFERROR(__xludf.DUMMYFUNCTION("""COMPUTED_VALUE"""),500.0) -> 500 | E26: =IFERROR(__xludf.DUMMYFUNCTION("""COMPUTED_VALUE"""),"Very Rare") -> Very Rare | G26: =IFERROR(__xludf.DUMMYFUNCTION("""COMPUTED_VALUE"""),"Wondrous Item") -> Wondrous Item | H26: =IFERROR(__xludf.DUMMYFUNCTION("""COMPUTED_VALUE"""),"Holding this stick fills you with an insurmountable urge to try to break it. You must use your action and make a DC 22 Strength check to attempt to break it. If you fail, you throw the stick 20 feet in a random direction. If you succeed, your strength sco"&"re becomes 20 for 24 hours, and you enter a Rage, as the Barbarian trait.") -> Holding this stick fills you with an insurmountable urge to try to break it. You must use your action and make a DC 22 Strength check to attempt to break it. If you fail, you throw the stick 20 feet in a random direction. If you succeed, your strength score becomes 20 for 24 hours, and you enter a Rage, as the Barbarian trait. | J26: =IFERROR(__xludf.DUMMYFUNCTION("""COMPUTED_VALUE"""),"/u/gimme_some_sunshine") -> /u/gimme_some_sunshine | K26: =IFERROR(__xludf.DUMMYFUNCTION("""COMPUTED_VALUE"""),5.0) -> 5
A27: 100 | B27: =IFERROR(__xludf.DUMMYFUNCTION("""COMPUTED_VALUE"""),"The Blaze of Glory") -> The Blaze of Glory | C27: =IFERROR(__xludf.DUMMYFUNCTION("""COMPUTED_VALUE"""),"A heavy, simple platinum torch that will not ignite under normal circumstances.") -> A heavy, simple platinum torch that will not ignite under normal circumstances. | D27: =IFERROR(__xludf.DUMMYFUNCTION("""COMPUTED_VALUE"""),8000.0) -> 8000 | E27: =IFERROR(__xludf.DUMMYFUNCTION("""COMPUTED_VALUE"""),"Very Rare") -> Very Rare | G27: =IFERROR(__xludf.DUMMYFUNCTION("""COMPUTED_VALUE"""),"Wondrous Item") -> Wondrous Item | H27: =IFERROR(__xludf.DUMMYFUNCTION("""COMPUTED_VALUE"""),"A willing creature holding this item may choose to ignite it at will. When you do, you are consumed by a brilliant white flame and you lose all of your remaining hit points, and then suffer damage equal to your maximum hit points. Up to 3 targets within 5"&"0 feet each take radiant damage equal to 1d10 damage per character level that you have, plus half of your maximum hit points, or half that amount on a successful Dexterity save (DC17). The torch becomes mundane after this effect takes place.") -> A willing creature holding this item may choose to ignite it at will. When you do, you are consumed by a brilliant white flame and you lose all of your remaining hit points, and then suffer damage equal to your maximum hit points. Up to 3 targets within 50 feet each take radiant damage equal to 1d10 damage per character level that you have, plus half of your maximum hit points, or half that amount on a successful Dexterity save (DC17). The torch becomes mundane after this effect takes place. | J27: =IFERROR(__xludf.DUMMYFUNCTION("""COMPUTED_VALUE"""),"/u/gimme_some_sunshine") -> /u/gimme_some_sunshine | K27: =IFERROR(__xludf.DUMMYFUNCTION("""COMPUTED_VALUE"""),5.0) -> 5
B28: =IFERROR(__xludf.DUMMYFUNCTION("""COMPUTED_VALUE"""),"The Olm Shield") -> The Olm Shield | C28: =IFERROR(__xludf.DUMMYFUNCTION("""COMPUTED_VALUE"""),"A circular shield with an amber edge, and covered in a lustrous, gold-colored metal. On the face of the shield is a depiction of a man destroying a dragon while the dragon destroys the man, as in an ouroboros.") -> A circular shield with an amber edge, and covered in a lustrous, gold-colored metal. On the face of the shield is a depiction of a man destroying a dragon while the dragon destroys the man, as in an ouroboros. | D28: =IFERROR(__xludf.DUMMYFUNCTION("""COMPUTED_VALUE"""),1500.0) -> 1500 | E28: =IFERROR(__xludf.DUMMYFUNCTION("""COMPUTED_VALUE"""),"Very Rare") -> Very Rare | G28: =IFERROR(__xludf.DUMMYFUNCTION("""COMPUTED_VALUE"""),"Armor") -> Armor | H28: =IFERROR(__xludf.DUMMYFUNCTION("""COMPUTED_VALUE"""),"Grants +2 AC when equipped. While carried, it grants immunity to fear effects, and you have advantage on Charisma skill checks to inspire others. If the shield is struck with Dragonfire, the bearer is enveloped with amber scales, grants resistance to fire"&" damage, increases size by 1 category, and grants a fly speed of 60 for as long as you remain in combat.") -> Grants +2 AC when equipped. While carried, it grants immunity to fear effects, and you have advantage on Charisma skill checks to inspire others. If the shield is struck with Dragonfire, the bearer is enveloped with amber scales, grants resistance to fire damage, increases size by 1 category, and grants a fly speed of 60 for as long as you remain in combat. | J28: =IFERROR(__xludf.DUMMYFUNCTION("""COMPUTED_VALUE"""),"/u/gimme_some_sunshine") -> /u/gimme_some_sunshine | K28: =IFERROR(__xludf.DUMMYFUNCTION("""COMPUTED_VALUE"""),5.0) -> 5
B29: =IFERROR(__xludf.DUMMYFUNCTION("""COMPUTED_VALUE"""),"Quelling Axe") -> Quelling Axe | C29: =IFERROR(__xludf.DUMMYFUNCTION("""COMPUTED_VALUE"""),"This axe appears to be like any other felling axe, but when used it will unerringly cut down any tree with one swing. Its formidable weight and uneven balancing make it a slow, inefficient weapon.") -> This axe appears to be like any other felling axe, but when used it will unerringly cut down any tree with one swing. Its formidable weight and uneven balancing make it a slow, inefficient weapon. | D29: =IFERROR(__xludf.DUMMYFUNCTION("""COMPUTED_VALUE"""),7000.0) -> 7000 | E29: =IFERROR(__xludf.DUMMYFUNCTION("""COMPUTED_VALUE"""),"Very Rare") -> Very Rare | F29: =IFERROR(__xludf.DUMMYFUNCTION("""COMPUTED_VALUE"""),10.0) -> 10 | G29: =IFERROR(__xludf.DUMMYFUNCTION("""COMPUTED_VALUE"""),"Wondrous Item") -> Wondrous Item | H29: =IFERROR(__xludf.DUMMYFUNCTION("""COMPUTED_VALUE"""),"1d10 Slashing - Martial - Heavy, Two-Handed") -> 1d10 Slashing - Martial - Heavy, Two-Handed | I29: =IFERROR(__xludf.DUMMYFUNCTION("""COMPUTED_VALUE"""),"Requires Attunement") -> Requires Attunement | J29: =IFERROR(__xludf.DUMMYFUNCTION("""COMPUTED_VALUE"""),"DOTA2") -> DOTA2 | K29: =IFERROR(__xludf.DUMMYFUNCTION("""COMPUTED_VALUE"""),5.0) -> 5
B30: =IFERROR(__xludf.DUMMYFUNCTION("""COMPUTED_VALUE"""),"Psyche of Strife") -> Psyche of Strife | C30: =IFERROR(__xludf.DUMMYFUNCTION("""COMPUTED_VALUE"""),"A tall mirror in ornate silvery frame with perfectly reflecting surface. The ornaments depicting faceless humanoids locked in battle. ") -> A tall mirror in ornate silvery frame with perfectly reflecting surface. The ornaments depicting faceless humanoids locked in battle. | D30: =IFERROR(__xludf.DUMMYFUNCTION("""COMPUTED_VALUE"""),15000.0) -> 15000 | E30: =IFERROR(__xludf.DUMMYFUNCTION("""COMPUTED_VALUE"""),"Very Rare") -> Very Rare | F30: =IFERROR(__xludf.DUMMYFUNCTION("""COMPUTED_VALUE"""),70.0) -> 70 | G30: =IFERROR(__xludf.DUMMYFUNCTION("""COMPUTED_VALUE"""),"Wondrous Item") -> Wondrous Item | H30: =IFERROR(__xludf.DUMMYFUNCTION("""COMPUTED_VALUE"""),"Anyone who looks into the mirror will see their own perfect reflection. However, when the first character takes a glimpse on someone else's image, they will see a horrifying visage of a powerful monster (lich, mind flayer, etc.), likely to be found in the"&" complex where the Psyche is located. This effect is commanded by a demonic intelligence imprisoned in the shiny surface, and will occur in a manner to cause maximum confusion, mistrust and likely infighting to bands of adventurers. It's very easy to shat"&"ter the mirror, however all the fragments will have the same tendency to occasionally show your best friend as a rotting undead - only to you.") -> Anyone who looks into the mirror will see their own perfect reflection. However, when the first character takes a glimpse on someone else's image, they will see a horrifying visage of a powerful monster (lich, mind flayer, etc.), likely to be found in the complex where the Psyche is located. This effect is commanded by a demonic intelligence imprisoned in the shiny surface, and will occur in a manner to cause maximum confusion, mistrust and likely infighting to bands of adventurers. It's very easy to shatter the mirror, however all the fragments will have the same tendency to occasionally show your best friend as a rotting undead - only to you. | J30: =IFERROR(__xludf.DUMMYFUNCTION("""COMPUTED_VALUE"""),"Rutin75") -> Rutin75 | K30: =IFERROR(__xludf.DUMMYFUNCTION("""COMPUTED_VALUE"""),5.0) -> 5
